[{"title":"李仰哲任上海纪委书记","url":"https://www.toutiao.com/amos_land_page/?category_name=topic_innerflow&event_type=hot_board&log_pb=%7B%22category_name%22%3A%22topic_innerflow%22%2C%22cluster_type%22%3A%228%22%2C%22enter_from%22%3A%22click_category%22%2C%22entrance_hotspot%22%3A%22outside%22%2C%22event_type%22%3A%22hot_board%22%2C%22hot_board_cluster_id%22%3A%227149555874711732256%22%2C%22hot_board_impr_id%22%3A%22202210031331410101512050810B60F123%22%2C%22jump_page%22%3A%22hot_board_page%22%2C%22location%22%3A%22news_hot_card%22%2C%22page_location%22%3A%22hot_board_page%22%2C%22rank%22%3A%221%22%2C%22source%22%3A%22trending_tab%22%2C%22style_id%22%3A%2240132%22%2C%22title%22%3A%22%E6%9D%8E%E4%BB%B0%E5%93%B2%E4%BB%BB%E4%B8%8A%E6%B5%B7%E7%BA%AA%E5%A7%94%E4%B9%A6%E8%AE%B0%22%7D&rank=1&style_id=40132&topic_id=7149555874711732256","hot":"5328699","icon":"https://p26.toutiaoimg.com/img/mosaic-legacy/2b29200041b9c651e8148~cs_noop.png","cover":"https://p3.toutiaoimg.com/img/top-static-files-outer/breaknews/7918a5a7-084a-4ea3-bef8-62b2d82e3ab9~cs_noop.png"},{"title":"国庆六公主陪你宅家云观影","url":"https://webcast-open.douyin.com/open/media_live/208823316033","hot":"4821606","icon":"","cover":"https://p6.toutiaoimg.com/img/top-static-files-outer/breaknews/f36e87e8-9833-405b-861b-e04ccefb9dcc~cs_noop.png"},{"title":"我国第四批预备航天员选拔工作启动","url":"https://www.toutiao.com/amos_land_page/?category_name=topic_innerflow&event_type=hot_board&log_pb=%7B%22category_name%22%3A%22topic_innerflow%22%2C%22cluster_type%22%3A%222%22%2C%22enter_from%22%3A%22click_category%22%2C%22entrance_hotspot%22%3A%22outside%22%2C%22event_type%22%3A%22hot_board%22%2C%22hot_board_cluster_id%22%3A%227149861042586288166%22%2C%22hot_board_impr_id%22%3A%22202210031331410101512050810B60F123%22%2C%22jump_page%22%3A%22hot_board_page%22%2C%22location%22%3A%22news_hot_card%22%2C%22page_location%22%3A%22hot_board_page%22%2C%22rank%22%3A%223%22%2C%22source%22%3A%22trending_tab%22%2C%22style_id%22%3A%2240132%22%2C%22title%22%3A%22%E6%88%91%E5%9B%BD%E7%AC%AC%E5%9B%9B%E6%89%B9%E9%A2%84%E5%A4%87%E8%88%AA%E5%A4%A9%E5%91%98%E9%80%89%E6%8B%94%E5%B7%A5%E4%BD%9C%E5%90%AF%E5%8A%A8%22%7D&rank=3&style_id=40132&topic_id=7149861042586288166","hot":"4362770","icon":"https://p3.toutiaoimg.com/img/mosaic-legacy/2b29200041b9c651e8148~cs_noop.png","cover":"https://p9.toutiaoimg.com/img/mosaic-legacy/2b29000036f8405561443~cs_noop.png"},{"title":"俄失去国际民用航空组织理事会席位","url":"https://www.toutiao.com/amos_land_page/?category_name=topic_innerflow&event_type=hot_board&log_pb=%7B%22category_name%22%3A%22topic_innerflow%22%2C%22cluster_type%22%3A%226%22%2C%22enter_from%22%3A%22click_category%22%2C%22entrance_hotspot%22%3A%22outside%22%2C%22event_type%22%3A%22hot_board%22%2C%22hot_board_cluster_id%22%3A%227149592552746778665%22%2C%22hot_board_impr_id%22%3A%22202210031331410101512050810B60F123%22%2C%22jump_page%22%3A%22hot_board_page%22%2C%22location%22%3A%22news_hot_card%22%2C%22page_location%22%3A%22hot_board_page%22%2C%22rank%22%3A%224%22%2C%22source%22%3A%22trending_tab%22%2C%22style_id%22%3A%2240132%22%2C%22title%22%3A%22%E4%BF%84%E5%A4%B1%E5%8E%BB%E5%9B%BD%E9%99%85%E6%B0%91%E7%94%A8%E8%88%AA%E7%A9%BA%E7%BB%84%E7%BB%87%E7%90%86%E4%BA%8B%E4%BC%9A%E5%B8%AD%E4%BD%8D%22%7D&rank=4&style_id=40132&topic_id=7149592552746778665","hot":"3947597","icon":"","cover":"https://p9.toutiaoimg.com/img/top-static-files-outer/breaknews/d7c44414-ecc2-4794-843e-a28f63b3ee4a~cs_noop.png"},{"title":"青岛地标“石老人”海蚀柱坍塌","url":"https://www.toutiao.com/amos_land_page/?category_name=topic_innerflow&event_type=hot_board&log_pb=%7B%22category_name%22%3A%22topic_innerflow%22%2C%22cluster_type%22%3A%229%22%2C%22enter_from%22%3A%22click_category%22%2C%22entrance_hotspot%22%3A%22outside%22%2C%22event_type%22%3A%22hot_board%22%2C%22hot_board_cluster_id%22%3A%227150096022323068943%22%2C%22hot_board_impr_id%22%3A%22202210031331410101512050810B60F123%22%2C%22jump_page%22%3A%22hot_board_page%22%2C%22location%22%3A%22news_hot_card%22%2C%22page_location%22%3A%22hot_board_page%22%2C%22rank%22%3A%225%22%2C%22source%22%3A%22trending_tab%22%2C%22style_id%22%3A%2240132%22%2C%22title%22%3A%22%E9%9D%92%E5%B2%9B%E5%9C%B0%E6%A0%87%E2%80%9C%E7%9F%B3%E8%80%81%E4%BA%BA%E2%80%9D%E6%B5%B7%E8%9A%80%E6%9F%B1%E5%9D%8D%E5%A1%8C%22%7D&rank=5&style_id=40132&topic_id=7150096022323068943","hot":"3571933","icon":"https://p3.toutiaoimg.com/img/mosaic-legacy/2b29200041b9c651e8148~cs_noop.png","cover":"https://p3.toutiaoimg.com/img/top-static-files-outer/breaknews/bce63586-f0a3-4895-a05a-026a85a37a1d~cs_noop.png"},{"title":"海天酱油回应添加剂争议：符合国标","url":"https://www.toutiao.com/amos_land_page/?category_name=topic_innerflow&event_type=hot_board&log_pb=%7B%22category_name%22%3A%22topic_innerflow%22%2C%22cluster_type%22%3A%221%22%2C%22enter_from%22%3A%22click_category%22%2C%22entrance_hotspot%22%3A%22outside%22%2C%22event_type%22%3A%22hot_board%22%2C%22hot_board_cluster_id%22%3A%227143540377100881445%22%2C%22hot_board_impr_id%22%3A%22202210031331410101512050810B60F123%22%2C%22jump_page%22%3A%22hot_board_page%22%2C%22location%22%3A%22news_hot_card%22%2C%22page_location%22%3A%22hot_board_page%22%2C%22rank%22%3A%226%22%2C%22source%22%3A%22trending_tab%22%2C%22style_id%22%3A%2240132%22%2C%22title%22%3A%22%E6%B5%B7%E5%A4%A9%E9%85%B1%E6%B2%B9%E5%9B%9E%E5%BA%94%E6%B7%BB%E5%8A%A0%E5%89%82%E4%BA%89%E8%AE%AE%EF%BC%9A%E7%AC%A6%E5%90%88%E5%9B%BD%E6%A0%87%22%7D&rank=6&style_id=40132&topic_id=7143540377100881445","hot":"3232019","icon":"","cover":"https://p26.toutiaoimg.com/img/top-static-files-outer/breaknews/1f112d0b-ed32-4a55-a6a3-7795a4cef3cf~cs_noop.png"},{"title":"英国超50城爆发游行 抗议物价飞涨","url":"https://www.toutiao.com/amos_land_page/?category_name=topic_innerflow&event_type=hot_board&log_pb=%7B%22category_name%22%3A%22topic_innerflow%22%2C%22cluster_type%22%3A%2210%22%2C%22enter_from%22%3A%22click_category%22%2C%22entrance_hotspot%22%3A%22outside%22%2C%22event_type%22%3A%22hot_board%22%2C%22hot_board_cluster_id%22%3A%227150086683210288677%22%2C%22hot_board_impr_id%22%3A%22202210031331410101512050810B60F123%22%2C%22jump_page%22%3A%22hot_board_page%22%2C%22location%22%3A%22news_hot_card%22%2C%22page_location%22%3A%22hot_board_page%22%2C%22rank%22%3A%227%22%2C%22source%22%3A%22trending_tab%22%2C%22style_id%22%3A%2240132%22%2C%22title%22%3A%22%E8%8B%B1%E5%9B%BD%E8%B6%8550%E5%9F%8E%E7%88%86%E5%8F%91%E6%B8%B8%E8%A1%8C+%E6%8A%97%E8%AE%AE%E7%89%A9%E4%BB%B7%E9%A3%9E%E6%B6%A8%22%7D&rank=7&style_id=40132&topic_id=7150086683210288677","hot":"2924452","icon":"https://p6.toutiaoimg.com/img/mosaic-legacy/2b29200041b9c651e8148~cs_noop.png","cover":"https://p26.toutiaoimg.com/img/tos-cn-i-qvj2lq49k0/9d5cf08e90d5461a8c8dd246cbf2e683~cs_noop.png"},{"title":"寒潮天气将终结南方高温","url":"https://www.toutiao.com/amos_land_page/?category_name=topic_innerflow&event_type=hot_board&log_pb=%7B%22category_name%22%3A%22topic_innerflow%22%2C%22cluster_type%22%3A%222%22%2C%22enter_from%22%3A%22click_category%22%2C%22entrance_hotspot%22%3A%22outside%22%2C%22event_type%22%3A%22hot_board%22%2C%22hot_board_cluster_id%22%3A%227149802643970326539%22%2C%22hot_board_impr_id%22%3A%22202210031331410101512050810B60F123%22%2C%22jump_page%22%3A%22hot_board_page%22%2C%22location%22%3A%22news_hot_card%22%2C%22page_location%22%3A%22hot_board_page%22%2C%22rank%22%3A%228%22%2C%22source%22%3A%22trending_tab%22%2C%22style_id%22%3A%2240132%22%2C%22title%22%3A%22%E5%AF%92%E6%BD%AE%E5%A4%A9%E6%B0%94%E5%B0%86%E7%BB%88%E7%BB%93%E5%8D%97%E6%96%B9%E9%AB%98%E6%B8%A9%22%7D&rank=8&style_id=40132&topic_id=7149802643970326539","hot":"2646153","icon":"","cover":"https://p3.toutiaoimg.com/img/tos-cn-i-qvj2lq49k0/260f77283ad141cea6ad6c42fa61b6f3~cs_noop.png"},{"title":"泽连斯基称乌克兰将开始重建海军","url":"https://www.toutiao.com/amos_land_page/?category_name=topic_innerflow&event_type=hot_board&log_pb=%7B%22category_name%22%3A%22topic_innerflow%22%2C%22cluster_type%22%3A%226%22%2C%22enter_from%22%3A%22click_category%22%2C%22entrance_hotspot%22%3A%22outside%22%2C%22event_type%22%3A%22hot_board%22%2C%22hot_board_cluster_id%22%3A%227149969098368106528%22%2C%22hot_board_impr_id%22%3A%22202210031331410101512050810B60F123%22%2C%22jump_page%22%3A%22hot_board_page%22%2C%22location%22%3A%22news_hot_card%22%2C%22page_location%22%3A%22hot_board_page%22%2C%22rank%22%3A%229%22%2C%22source%22%3A%22trending_tab%22%2C%22style_id%22%3A%2240132%22%2C%22title%22%3A%22%E6%B3%BD%E8%BF%9E%E6%96%AF%E5%9F%BA%E7%A7%B0%E4%B9%8C%E5%85%8B%E5%85%B0%E5%B0%86%E5%BC%80%E5%A7%8B%E9%87%8D%E5%BB%BA%E6%B5%B7%E5%86%9B%22%7D&rank=9&style_id=40132&topic_id=7149969098368106528","hot":"2394338","icon":"","cover":"https://p26.toutiaoimg.com/img/top-static-files-outer/breaknews/c922958f-1fc2-45be-a0fb-b027a1961c3c~cs_noop.png"},{"title":"俄罗斯失守利曼意味着什么","url":"https://www.toutiao.com/amos_land_page/?category_name=topic_innerflow&event_type=hot_board&log_pb=%7B%22category_name%22%3A%22topic_innerflow%22%2C%22cluster_type%22%3A%221%22%2C%22enter_from%22%3A%22click_category%22%2C%22entrance_hotspot%22%3A%22outside%22%2C%22event_type%22%3A%22hot_board%22%2C%22hot_board_cluster_id%22%3A%227149893458562383887%22%2C%22hot_board_impr_id%22%3A%22202210031331410101512050810B60F123%22%2C%22jump_page%22%3A%22hot_board_page%22%2C%22location%22%3A%22news_hot_card%22%2C%22page_location%22%3A%22hot_board_page%22%2C%22rank%22%3A%2210%22%2C%22source%22%3A%22trending_tab%22%2C%22style_id%22%3A%2240132%22%2C%22title%22%3A%22%E4%BF%84%E7%BD%97%E6%96%AF%E5%A4%B1%E5%AE%88%E5%88%A9%E6%9B%BC%E6%84%8F%E5%91%B3%E7%9D%80%E4%BB%80%E4%B9%88%22%7D&rank=10&style_id=40132&topic_id=7149893458562383887","hot":"1960318","icon":"https://p26.toutiaoimg.com/img/mosaic-legacy/2b29000041c9b5b3eff94~cs_noop.png","cover":"https://p26.toutiaoimg.com/img/top-static-files-outer/breaknews/b230985c-2bba-49ef-aca9-c02911312f25~cs_noop.png"},{"title":"石家庄发生4.3级地震","url":"https://www.toutiao.com/amos_land_page/?category_name=topic_innerflow&event_type=hot_board&log_pb=%7B%22category_name%22%3A%22topic_innerflow%22%2C%22cluster_type%22%3A%222%22%2C%22enter_from%22%3A%22click_category%22%2C%22entrance_hotspot%22%3A%22outside%22%2C%22event_type%22%3A%22hot_board%22%2C%22hot_board_cluster_id%22%3A%227149974338970583070%22%2C%22hot_board_impr_id%22%3A%22202210031331410101512050810B60F123%22%2C%22jump_page%22%3A%22hot_board_page%22%2C%22location%22%3A%22news_hot_card%22%2C%22page_location%22%3A%22hot_board_page%22%2C%22rank%22%3A%2211%22%2C%22source%22%3A%22trending_tab%22%2C%22style_id%22%3A%2240132%22%2C%22title%22%3A%22%E7%9F%B3%E5%AE%B6%E5%BA%84%E5%8F%91%E7%94%9F4.3%E7%BA%A7%E5%9C%B0%E9%9C%87%22%7D&rank=11&style_id=40132&topic_id=7149974338970583070","hot":"2166487","icon":"https://p6.toutiaoimg.com/img/mosaic-legacy/2b29200041b9c651e8148~cs_noop.png","cover":"https://p6.toutiaoimg.com/img/top-static-files-outer/breaknews/08d497fe-6a4f-4704-b9f2-5e6f42b66d90~cs_noop.png"},{"title":"2岁宝宝哭诉妈妈做饭难吃","url":"https://www.toutiao.com/amos_land_page/?category_name=topic_innerflow&event_type=hot_board&log_pb=%7B%22category_name%22%3A%22topic_innerflow%22%2C%22cluster_type%22%3A%220%22%2C%22enter_from%22%3A%22click_category%22%2C%22entrance_hotspot%22%3A%22outside%22%2C%22event_type%22%3A%22hot_board%22%2C%22hot_board_cluster_id%22%3A%227149868990527963136%22%2C%22hot_board_impr_id%22%3A%22202210031331410101512050810B60F123%22%2C%22jump_page%22%3A%22hot_board_page%22%2C%22location%22%3A%22news_hot_card%22%2C%22page_location%22%3A%22hot_board_page%22%2C%22rank%22%3A%2212%22%2C%22source%22%3A%22trending_tab%22%2C%22style_id%22%3A%2240132%22%2C%22title%22%3A%222%E5%B2%81%E5%AE%9D%E5%AE%9D%E5%93%AD%E8%AF%89%E5%A6%88%E5%A6%88%E5%81%9A%E9%A5%AD%E9%9A%BE%E5%90%83%22%7D&rank=12&style_id=40132&topic_id=7149868990527963136","hot":"1773769","icon":"","cover":"https://p26.toutiaoimg.com/img/top-static-files-outer/breaknews/e062449e-45bc-4bc7-85e2-403e37304f3b~cs_noop.png"},{"title":"楼上常深夜响动 女子放音箱反击","url":"https://www.toutiao.com/amos_land_page/?category_name=topic_innerflow&event_type=hot_board&log_pb=%7B%22category_name%22%3A%22topic_innerflow%22%2C%22cluster_type%22%3A%222%22%2C%22enter_from%22%3A%22click_category%22%2C%22entrance_hotspot%22%3A%22outside%22%2C%22event_type%22%3A%22hot_board%22%2C%22hot_board_cluster_id%22%3A%227149865538120843295%22%2C%22hot_board_impr_id%22%3A%22202210031331410101512050810B60F123%22%2C%22jump_page%22%3A%22hot_board_page%22%2C%22location%22%3A%22news_hot_card%22%2C%22page_location%22%3A%22hot_board_page%22%2C%22rank%22%3A%2213%22%2C%22source%22%3A%22trending_tab%22%2C%22style_id%22%3A%2240132%22%2C%22title%22%3A%22%E6%A5%BC%E4%B8%8A%E5%B8%B8%E6%B7%B1%E5%A4%9C%E5%93%8D%E5%8A%A8+%E5%A5%B3%E5%AD%90%E6%94%BE%E9%9F%B3%E7%AE%B1%E5%8F%8D%E5%87%BB%22%7D&rank=13&style_id=40132&topic_id=7149865538120843295","hot":"1604973","icon":"","cover":"https://p3.toutiaoimg.com/img/top-static-files-outer/breaknews/9d8fbb2b-6cf1-4da1-b0b3-fa784b6e31ad~cs_noop.png"},{"title":"英媒：特拉斯新政府可能败局已定","url":"https://www.toutiao.com/amos_land_page/?category_name=topic_innerflow&event_type=hot_board&log_pb=%7B%22category_name%22%3A%22topic_innerflow%22%2C%22cluster_type%22%3A%226%22%2C%22enter_from%22%3A%22click_category%22%2C%22entrance_hotspot%22%3A%22outside%22%2C%22event_type%22%3A%22hot_board%22%2C%22hot_board_cluster_id%22%3A%227149886446940848166%22%2C%22hot_board_impr_id%22%3A%22202210031331410101512050810B60F123%22%2C%22jump_page%22%3A%22hot_board_page%22%2C%22location%22%3A%22news_hot_card%22%2C%22page_location%22%3A%22hot_board_page%22%2C%22rank%22%3A%2214%22%2C%22source%22%3A%22trending_tab%22%2C%22style_id%22%3A%2240132%22%2C%22title%22%3A%22%E8%8B%B1%E5%AA%92%EF%BC%9A%E7%89%B9%E6%8B%89%E6%96%AF%E6%96%B0%E6%94%BF%E5%BA%9C%E5%8F%AF%E8%83%BD%E8%B4%A5%E5%B1%80%E5%B7%B2%E5%AE%9A%22%7D&rank=14&style_id=40132&topic_id=7149886446940848166","hot":"1452239","icon":"","cover":"https://p26.toutiaoimg.com/img/top-static-files-outer/breaknews/a4d887ec-33d5-4ba6-9969-23058ce942cc~cs_noop.png"},{"title":"女子二婚嫁初恋 各带儿女组6口之家","url":"https://www.toutiao.com/amos_land_page/?category_name=topic_innerflow&event_type=hot_board&log_pb=%7B%22category_name%22%3A%22topic_innerflow%22%2C%22cluster_type%22%3A%222%22%2C%22enter_from%22%3A%22click_category%22%2C%22entrance_hotspot%22%3A%22outside%22%2C%22event_type%22%3A%22hot_board%22%2C%22hot_board_cluster_id%22%3A%227149897521681301517%22%2C%22hot_board_impr_id%22%3A%22202210031331410101512050810B60F123%22%2C%22jump_page%22%3A%22hot_board_page%22%2C%22location%22%3A%22news_hot_card%22%2C%22page_location%22%3A%22hot_board_page%22%2C%22rank%22%3A%2215%22%2C%22source%22%3A%22trending_tab%22%2C%22style_id%22%3A%2240132%22%2C%22title%22%3A%22%E5%A5%B3%E5%AD%90%E4%BA%8C%E5%A9%9A%E5%AB%81%E5%88%9D%E6%81%8B+%E5%90%84%E5%B8%A6%E5%84%BF%E5%A5%B3%E7%BB%846%E5%8F%A3%E4%B9%8B%E5%AE%B6%22%7D&rank=15&style_id=40132&topic_id=7149897521681301517","hot":"1314041","icon":"","cover":"https://p6.toutiaoimg.com/img/top-static-files-outer/breaknews/4f2750c7-eadd-42b8-a49c-5720eae47b59~cs_noop.png"},{"title":"导演饶晓志谈万里归途请吴京演彩蛋","url":"https://www.toutiao.com/amos_land_page/?category_name=topic_innerflow&event_type=hot_board&log_pb=%7B%22category_name%22%3A%22topic_innerflow%22%2C%22cluster_type%22%3A%221%22%2C%22enter_from%22%3A%22click_category%22%2C%22entrance_hotspot%22%3A%22outside%22%2C%22event_type%22%3A%22hot_board%22%2C%22hot_board_cluster_id%22%3A%227150069205499379727%22%2C%22hot_board_impr_id%22%3A%22202210031331410101512050810B60F123%22%2C%22jump_page%22%3A%22hot_board_page%22%2C%22location%22%3A%22news_hot_card%22%2C%22page_location%22%3A%22hot_board_page%22%2C%22rank%22%3A%2216%22%2C%22source%22%3A%22trending_tab%22%2C%22style_id%22%3A%2240132%22%2C%22title%22%3A%22%E5%AF%BC%E6%BC%94%E9%A5%B6%E6%99%93%E5%BF%97%E8%B0%88%E4%B8%87%E9%87%8C%E5%BD%92%E9%80%94%E8%AF%B7%E5%90%B4%E4%BA%AC%E6%BC%94%E5%BD%A9%E8%9B%8B%22%7D&rank=16&style_id=40132&topic_id=7150069205499379727","hot":"1188993","icon":"","cover":"https://p6.toutiaoimg.com/img/top-static-files-outer/breaknews/cb3a47f4-a406-4891-ac64-d91fd8f8af76~cs_noop.png"},{"title":"高校研究：肥胖和住哪儿有关","url":"https://www.toutiao.com/amos_land_page/?category_name=topic_innerflow&event_type=hot_board&log_pb=%7B%22category_name%22%3A%22topic_innerflow%22%2C%22cluster_type%22%3A%222%22%2C%22enter_from%22%3A%22click_category%22%2C%22entrance_hotspot%22%3A%22outside%22%2C%22event_type%22%3A%22hot_board%22%2C%22hot_board_cluster_id%22%3A%227149868330194010143%22%2C%22hot_board_impr_id%22%3A%22202210031331410101512050810B60F123%22%2C%22jump_page%22%3A%22hot_board_page%22%2C%22location%22%3A%22news_hot_card%22%2C%22page_location%22%3A%22hot_board_page%22%2C%22rank%22%3A%2217%22%2C%22source%22%3A%22trending_tab%22%2C%22style_id%22%3A%2240132%22%2C%22title%22%3A%22%E9%AB%98%E6%A0%A1%E7%A0%94%E7%A9%B6%EF%BC%9A%E8%82%A5%E8%83%96%E5%92%8C%E4%BD%8F%E5%93%AA%E5%84%BF%E6%9C%89%E5%85%B3%22%7D&rank=17&style_id=40132&topic_id=7149868330194010143","hot":"1075845","icon":"","cover":"https://p3.toutiaoimg.com/img/top-static-files-outer/breaknews/2918f710-bd63-44a1-8809-0bee77137630~cs_noop.png"},{"title":"湖南一干部国庆值班擅离职守被处分","url":"https://www.toutiao.com/amos_land_page/?category_name=topic_innerflow&event_type=hot_board&log_pb=%7B%22category_name%22%3A%22topic_innerflow%22%2C%22cluster_type%22%3A%220%22%2C%22enter_from%22%3A%22click_category%22%2C%22entrance_hotspot%22%3A%22outside%22%2C%22event_type%22%3A%22hot_board%22%2C%22hot_board_cluster_id%22%3A%227149905526745202688%22%2C%22hot_board_impr_id%22%3A%22202210031331410101512050810B60F123%22%2C%22jump_page%22%3A%22hot_board_page%22%2C%22location%22%3A%22news_hot_card%22%2C%22page_location%22%3A%22hot_board_page%22%2C%22rank%22%3A%2218%22%2C%22source%22%3A%22trending_tab%22%2C%22style_id%22%3A%2240132%22%2C%22title%22%3A%22%E6%B9%96%E5%8D%97%E4%B8%80%E5%B9%B2%E9%83%A8%E5%9B%BD%E5%BA%86%E5%80%BC%E7%8F%AD%E6%93%85%E7%A6%BB%E8%81%8C%E5%AE%88%E8%A2%AB%E5%A4%84%E5%88%86%22%7D&rank=18&style_id=40132&topic_id=7149905526745202688","hot":"973465","icon":"https://p9.toutiaoimg.com/img/mosaic-legacy/2b29000041c9b5b3eff94~cs_noop.png","cover":"https://p26.toutiaoimg.com/img/tos-cn-i-qvj2lq49k0/abdc86ab1d0548d9822e131d024df02b~cs_noop.png"},{"title":"台媒：日本舰船骚扰台船只 对峙10小时","url":"https://www.toutiao.com/amos_land_page/?category_name=topic_innerflow&event_type=hot_board&log_pb=%7B%22category_name%22%3A%22topic_innerflow%22%2C%22cluster_type%22%3A%225%22%2C%22enter_from%22%3A%22click_category%22%2C%22entrance_hotspot%22%3A%22outside%22%2C%22event_type%22%3A%22hot_board%22%2C%22hot_board_cluster_id%22%3A%227150131758850117128%22%2C%22hot_board_impr_id%22%3A%22202210031331410101512050810B60F123%22%2C%22jump_page%22%3A%22hot_board_page%22%2C%22location%22%3A%22news_hot_card%22%2C%22page_location%22%3A%22hot_board_page%22%2C%22rank%22%3A%2219%22%2C%22source%22%3A%22trending_tab%22%2C%22style_id%22%3A%2240132%22%2C%22title%22%3A%22%E5%8F%B0%E5%AA%92%EF%BC%9A%E6%97%A5%E6%9C%AC%E8%88%B0%E8%88%B9%E9%AA%9A%E6%89%B0%E5%8F%B0%E8%88%B9%E5%8F%AA+%E5%AF%B9%E5%B3%9910%E5%B0%8F%E6%97%B6%22%7D&rank=19&style_id=40132&topic_id=7150131758850117128","hot":"880828","icon":"https://p3.toutiaoimg.com/img/mosaic-legacy/2b29000041c9b5b3eff94~cs_noop.png","cover":"https://p3.toutiaoimg.com/img/top-static-files-outer/breaknews/585f9d2b-f0d0-4ab7-b23f-32f32a1524b9~cs_noop.png"},{"title":"游客达最高承载量 多景区停止预约","url":"https://www.toutiao.com/amos_land_page/?category_name=topic_innerflow&event_type=hot_board&log_pb=%7B%22category_name%22%3A%22topic_innerflow%22%2C%22cluster_type%22%3A%222%22%2C%22enter_from%22%3A%22click_category%22%2C%22entrance_hotspot%22%3A%22outside%22%2C%22event_type%22%3A%22hot_board%22%2C%22hot_board_cluster_id%22%3A%227144985065797881358%22%2C%22hot_board_impr_id%22%3A%22202210031331410101512050810B60F123%22%2C%22jump_page%22%3A%22hot_board_page%22%2C%22location%22%3A%22news_hot_card%22%2C%22page_location%22%3A%22hot_board_page%22%2C%22rank%22%3A%2220%22%2C%22source%22%3A%22trending_tab%22%2C%22style_id%22%3A%2240132%22%2C%22title%22%3A%22%E6%B8%B8%E5%AE%A2%E8%BE%BE%E6%9C%80%E9%AB%98%E6%89%BF%E8%BD%BD%E9%87%8F+%E5%A4%9A%E6%99%AF%E5%8C%BA%E5%81%9C%E6%AD%A2%E9%A2%84%E7%BA%A6%22%7D&rank=20&style_id=40132&topic_id=7144985065797881358","hot":"797006","icon":"","cover":"https://p3.toutiaoimg.com/img/top-static-files-outer/breaknews/47a1b1a3-93fc-4eb9-a1ed-ee17fcbd71bd~cs_noop.png"},{"title":"十一婚礼扎堆 年轻人被份子钱掏空","url":"https://www.toutiao.com/amos_land_page/?category_name=topic_innerflow&event_type=hot_board&log_pb=%7B%22category_name%22%3A%22topic_innerflow%22%2C%22cluster_type%22%3A%221%22%2C%22enter_from%22%3A%22click_category%22%2C%22entrance_hotspot%22%3A%22outside%22%2C%22event_type%22%3A%22hot_board%22%2C%22hot_board_cluster_id%22%3A%227150109025546272780%22%2C%22hot_board_impr_id%22%3A%22202210031331410101512050810B60F123%22%2C%22jump_page%22%3A%22hot_board_page%22%2C%22location%22%3A%22news_hot_card%22%2C%22page_location%22%3A%22hot_board_page%22%2C%22rank%22%3A%2221%22%2C%22source%22%3A%22trending_tab%22%2C%22style_id%22%3A%2240132%22%2C%22title%22%3A%22%E5%8D%81%E4%B8%80%E5%A9%9A%E7%A4%BC%E6%89%8E%E5%A0%86+%E5%B9%B4%E8%BD%BB%E4%BA%BA%E8%A2%AB%E4%BB%BD%E5%AD%90%E9%92%B1%E6%8E%8F%E7%A9%BA%22%7D&rank=21&style_id=40132&topic_id=7150109025546272780","hot":"721161","icon":"","cover":"https://p6.toutiaoimg.com/img/top-static-files-outer/breaknews/e0bdb069-9c81-417c-a77d-4cc986ec8530~cs_noop.png"},{"title":"媒体：歼20晋级为五代意义重大","url":"https://www.toutiao.com/amos_land_page/?category_name=topic_innerflow&event_type=hot_board&log_pb=%7B%22category_name%22%3A%22topic_innerflow%22%2C%22cluster_type%22%3A%226%22%2C%22enter_from%22%3A%22click_category%22%2C%22entrance_hotspot%22%3A%22outside%22%2C%22event_type%22%3A%22hot_board%22%2C%22hot_board_cluster_id%22%3A%227150063678774050828%22%2C%22hot_board_impr_id%22%3A%22202210031331410101512050810B60F123%22%2C%22jump_page%22%3A%22hot_board_page%22%2C%22location%22%3A%22news_hot_card%22%2C%22page_location%22%3A%22hot_board_page%22%2C%22rank%22%3A%2222%22%2C%22source%22%3A%22trending_tab%22%2C%22style_id%22%3A%2240132%22%2C%22title%22%3A%22%E5%AA%92%E4%BD%93%EF%BC%9A%E6%AD%BC20%E6%99%8B%E7%BA%A7%E4%B8%BA%E4%BA%94%E4%BB%A3%E6%84%8F%E4%B9%89%E9%87%8D%E5%A4%A7%22%7D&rank=22&style_id=40132&topic_id=7150063678774050828","hot":"652533","icon":"","cover":"https://p9.toutiaoimg.com/img/tos-cn-i-qvj2lq49k0/ce641b841de844c9bc1765ae15d89f28~cs_noop.png"},{"title":"巴西总统大选首轮投票未决胜负","url":"https://www.toutiao.com/amos_land_page/?category_name=topic_innerflow&event_type=hot_board&log_pb=%7B%22category_name%22%3A%22topic_innerflow%22%2C%22cluster_type%22%3A%226%22%2C%22enter_from%22%3A%22click_category%22%2C%22entrance_hotspot%22%3A%22outside%22%2C%22event_type%22%3A%22hot_board%22%2C%22hot_board_cluster_id%22%3A%227150099590581223458%22%2C%22hot_board_impr_id%22%3A%22202210031331410101512050810B60F123%22%2C%22jump_page%22%3A%22hot_board_page%22%2C%22location%22%3A%22news_hot_card%22%2C%22page_location%22%3A%22hot_board_page%22%2C%22rank%22%3A%2223%22%2C%22source%22%3A%22trending_tab%22%2C%22style_id%22%3A%2240132%22%2C%22title%22%3A%22%E5%B7%B4%E8%A5%BF%E6%80%BB%E7%BB%9F%E5%A4%A7%E9%80%89%E9%A6%96%E8%BD%AE%E6%8A%95%E7%A5%A8%E6%9C%AA%E5%86%B3%E8%83%9C%E8%B4%9F%22%7D&rank=23&style_id=40132&topic_id=7150099590581223458","hot":"590436","icon":"","cover":"https://p6.toutiaoimg.com/img/tos-cn-i-qvj2lq49k0/0b37ffa077ed4a868808ffef04050bae~cs_noop.png"},{"title":"游客踩向日葵拍照 保安怒怼","url":"https://www.toutiao.com/amos_land_page/?category_name=topic_innerflow&event_type=hot_board&log_pb=%7B%22category_name%22%3A%22topic_innerflow%22%2C%22cluster_type%22%3A%222%22%2C%22enter_from%22%3A%22click_category%22%2C%22entrance_hotspot%22%3A%22outside%22%2C%22event_type%22%3A%22hot_board%22%2C%22hot_board_cluster_id%22%3A%227149840801164427294%22%2C%22hot_board_impr_id%22%3A%22202210031331410101512050810B60F123%22%2C%22jump_page%22%3A%22hot_board_page%22%2C%22location%22%3A%22news_hot_card%22%2C%22page_location%22%3A%22hot_board_page%22%2C%22rank%22%3A%2224%22%2C%22source%22%3A%22trending_tab%22%2C%22style_id%22%3A%2240132%22%2C%22title%22%3A%22%E6%B8%B8%E5%AE%A2%E8%B8%A9%E5%90%91%E6%97%A5%E8%91%B5%E6%8B%8D%E7%85%A7+%E4%BF%9D%E5%AE%89%E6%80%92%E6%80%BC%22%7D&rank=24&style_id=40132&topic_id=7149840801164427294","hot":"534249","icon":"https://p6.toutiaoimg.com/img/mosaic-legacy/2b29000041c9b5b3eff94~cs_noop.png","cover":"https://p26.toutiaoimg.com/img/mosaic-legacy/2b29000036f8405561443~cs_noop.png"},{"title":"《自然》子刊：多喝酒或易致人早衰","url":"https://www.toutiao.com/amos_land_page/?category_name=topic_innerflow&event_type=hot_board&log_pb=%7B%22category_name%22%3A%22topic_innerflow%22%2C%22cluster_type%22%3A%221%22%2C%22enter_from%22%3A%22click_category%22%2C%22entrance_hotspot%22%3A%22outside%22%2C%22event_type%22%3A%22hot_board%22%2C%22hot_board_cluster_id%22%3A%227149918628048011301%22%2C%22hot_board_impr_id%22%3A%22202210031331410101512050810B60F123%22%2C%22jump_page%22%3A%22hot_board_page%22%2C%22location%22%3A%22news_hot_card%22%2C%22page_location%22%3A%22hot_board_page%22%2C%22rank%22%3A%2225%22%2C%22source%22%3A%22trending_tab%22%2C%22style_id%22%3A%2240132%22%2C%22title%22%3A%22%E3%80%8A%E8%87%AA%E7%84%B6%E3%80%8B%E5%AD%90%E5%88%8A%EF%BC%9A%E5%A4%9A%E5%96%9D%E9%85%92%E6%88%96%E6%98%93%E8%87%B4%E4%BA%BA%E6%97%A9%E8%A1%B0%22%7D&rank=25&style_id=40132&topic_id=7149918628048011301","hot":"483408","icon":"","cover":"https://p9.toutiaoimg.com/img/top-static-files-outer/breaknews/7ba58a3e-d895-4cee-ba8a-f6bdddb4448c~cs_noop.png"},{"title":"西媒：乌东四地入俄或带来三种场景","url":"https://www.toutiao.com/amos_land_page/?category_name=topic_innerflow&event_type=hot_board&log_pb=%7B%22category_name%22%3A%22topic_innerflow%22%2C%22cluster_type%22%3A%226%22%2C%22enter_from%22%3A%22click_category%22%2C%22entrance_hotspot%22%3A%22outside%22%2C%22event_type%22%3A%22hot_board%22%2C%22hot_board_cluster_id%22%3A%227150102880509722654%22%2C%22hot_board_impr_id%22%3A%22202210031331410101512050810B60F123%22%2C%22jump_page%22%3A%22hot_board_page%22%2C%22location%22%3A%22news_hot_card%22%2C%22page_location%22%3A%22hot_board_page%22%2C%22rank%22%3A%2226%22%2C%22source%22%3A%22trending_tab%22%2C%22style_id%22%3A%2240132%22%2C%22title%22%3A%22%E8%A5%BF%E5%AA%92%EF%BC%9A%E4%B9%8C%E4%B8%9C%E5%9B%9B%E5%9C%B0%E5%85%A5%E4%BF%84%E6%88%96%E5%B8%A6%E6%9D%A5%E4%B8%89%E7%A7%8D%E5%9C%BA%E6%99%AF%22%7D&rank=26&style_id=40132&topic_id=7150102880509722654","hot":"437406","icon":"https://p6.toutiaoimg.com/img/mosaic-legacy/2b29000041c9b5b3eff94~cs_noop.png","cover":"https://p26.toutiaoimg.com/img/mosaic-legacy/2b29000036f8405561443~cs_noop.png"},{"title":"31省份昨增本土189+466例","url":"https://www.toutiao.com/amos_land_page/?category_name=topic_innerflow&event_type=hot_board&log_pb=%7B%22category_name%22%3A%22topic_innerflow%22%2C%22cluster_type%22%3A%222%22%2C%22enter_from%22%3A%22click_category%22%2C%22entrance_hotspot%22%3A%22outside%22%2C%22event_type%22%3A%22hot_board%22%2C%22hot_board_cluster_id%22%3A%227149033553383165470%22%2C%22hot_board_impr_id%22%3A%22202210031331410101512050810B60F123%22%2C%22jump_page%22%3A%22hot_board_page%22%2C%22location%22%3A%22news_hot_card%22%2C%22page_location%22%3A%22hot_board_page%22%2C%22rank%22%3A%2227%22%2C%22source%22%3A%22trending_tab%22%2C%22style_id%22%3A%2240132%22%2C%22title%22%3A%2231%E7%9C%81%E4%BB%BD%E6%98%A8%E5%A2%9E%E6%9C%AC%E5%9C%9F189%2B466%E4%BE%8B%22%7D&rank=27&style_id=40132&topic_id=7149033553383165470","hot":"395781","icon":"","cover":"https://p3.toutiaoimg.com/img/top-static-files-outer/breaknews/1dd78965-74c3-4d3b-ac77-9a568760b4a3~cs_noop.png"},{"title":"年轻人假期搞钱：喂猫一周赚5000","url":"https://www.toutiao.com/amos_land_page/?category_name=topic_innerflow&event_type=hot_board&log_pb=%7B%22category_name%22%3A%22topic_innerflow%22%2C%22cluster_type%22%3A%228%22%2C%22enter_from%22%3A%22click_category%22%2C%22entrance_hotspot%22%3A%22outside%22%2C%22event_type%22%3A%22hot_board%22%2C%22hot_board_cluster_id%22%3A%227149713453932871721%22%2C%22hot_board_impr_id%22%3A%22202210031331410101512050810B60F123%22%2C%22jump_page%22%3A%22hot_board_page%22%2C%22location%22%3A%22news_hot_card%22%2C%22page_location%22%3A%22hot_board_page%22%2C%22rank%22%3A%2228%22%2C%22source%22%3A%22trending_tab%22%2C%22style_id%22%3A%2240132%22%2C%22title%22%3A%22%E5%B9%B4%E8%BD%BB%E4%BA%BA%E5%81%87%E6%9C%9F%E6%90%9E%E9%92%B1%EF%BC%9A%E5%96%82%E7%8C%AB%E4%B8%80%E5%91%A8%E8%B5%9A5000%22%7D&rank=28&style_id=40132&topic_id=7149713453932871721","hot":"358117","icon":"","cover":"https://p3.toutiaoimg.com/img/top-static-files-outer/breaknews/6613a4e4-ef23-4b0d-88ad-895e89f23584~cs_noop.png"},{"title":"男生发现宿舍地板下暗藏地道","url":"https://www.toutiao.com/amos_land_page/?category_name=topic_innerflow&event_type=hot_board&log_pb=%7B%22category_name%22%3A%22topic_innerflow%22%2C%22cluster_type%22%3A%2210%22%2C%22enter_from%22%3A%22click_category%22%2C%22entrance_hotspot%22%3A%22outside%22%2C%22event_type%22%3A%22hot_board%22%2C%22hot_board_cluster_id%22%3A%227149811608292691460%22%2C%22hot_board_impr_id%22%3A%22202210031331410101512050810B60F123%22%2C%22jump_page%22%3A%22hot_board_page%22%2C%22location%22%3A%22news_hot_card%22%2C%22page_location%22%3A%22hot_board_page%22%2C%22rank%22%3A%2229%22%2C%22source%22%3A%22trending_tab%22%2C%22style_id%22%3A%2240132%22%2C%22title%22%3A%22%E7%94%B7%E7%94%9F%E5%8F%91%E7%8E%B0%E5%AE%BF%E8%88%8D%E5%9C%B0%E6%9D%BF%E4%B8%8B%E6%9A%97%E8%97%8F%E5%9C%B0%E9%81%93%22%7D&rank=29&style_id=40132&topic_id=7149811608292691460","hot":"324038","icon":"","cover":"https://p9.toutiaoimg.com/img/top-static-files-outer/breaknews/94fcd57e-5d26-4ee6-ba35-59539592a7c3~cs_noop.png"},{"title":"女子花5千买床却称不敢睡","url":"https://www.toutiao.com/amos_land_page/?category_name=topic_innerflow&event_type=hot_board&log_pb=%7B%22category_name%22%3A%22topic_innerflow%22%2C%22cluster_type%22%3A%221%22%2C%22enter_from%22%3A%22click_category%22%2C%22entrance_hotspot%22%3A%22outside%22%2C%22event_type%22%3A%22hot_board%22%2C%22hot_board_cluster_id%22%3A%227150087013587386403%22%2C%22hot_board_impr_id%22%3A%22202210031331410101512050810B60F123%22%2C%22jump_page%22%3A%22hot_board_page%22%2C%22location%22%3A%22news_hot_card%22%2C%22page_location%22%3A%22hot_board_page%22%2C%22rank%22%3A%2230%22%2C%22source%22%3A%22trending_tab%22%2C%22style_id%22%3A%2240132%22%2C%22title%22%3A%22%E5%A5%B3%E5%AD%90%E8%8A%B15%E5%8D%83%E4%B9%B0%E5%BA%8A%E5%8D%B4%E7%A7%B0%E4%B8%8D%E6%95%A2%E7%9D%A1%22%7D&rank=30&style_id=40132&topic_id=7150087013587386403","hot":"293202","icon":"","cover":"https://p26.toutiaoimg.com/img/top-static-files-outer/breaknews/3050df48-5331-41f8-8334-09a5029fefcd~cs_noop.png"},{"title":"诺贝尔奖将揭晓 这些华人科学家被看好","url":"https://www.toutiao.com/amos_land_page/?category_name=topic_innerflow&event_type=hot_board&log_pb=%7B%22category_name%22%3A%22topic_innerflow%22%2C%22cluster_type%22%3A%228%22%2C%22enter_from%22%3A%22click_category%22%2C%22entrance_hotspot%22%3A%22outside%22%2C%22event_type%22%3A%22hot_board%22%2C%22hot_board_cluster_id%22%3A%227149889991022215198%22%2C%22hot_board_impr_id%22%3A%22202210031331410101512050810B60F123%22%2C%22jump_page%22%3A%22hot_board_page%22%2C%22location%22%3A%22news_hot_card%22%2C%22page_location%22%3A%22hot_board_page%22%2C%22rank%22%3A%2231%22%2C%22source%22%3A%22trending_tab%22%2C%22style_id%22%3A%2240132%22%2C%22title%22%3A%22%E8%AF%BA%E8%B4%9D%E5%B0%94%E5%A5%96%E5%B0%86%E6%8F%AD%E6%99%93+%E8%BF%99%E4%BA%9B%E5%8D%8E%E4%BA%BA%E7%A7%91%E5%AD%A6%E5%AE%B6%E8%A2%AB%E7%9C%8B%E5%A5%BD%22%7D&rank=31&style_id=40132&topic_id=7149889991022215198","hot":"265300","icon":"","cover":"https://p3.toutiaoimg.com/img/top-static-files-outer/breaknews/c7a3b193-7437-4a8e-b4c6-57dc03bada43~cs_noop.png"},{"title":"NBA季前赛爆大冷：太阳不敌NBL队","url":"https://www.toutiao.com/amos_land_page/?category_name=topic_innerflow&event_type=hot_board&log_pb=%7B%22category_name%22%3A%22topic_innerflow%22%2C%22cluster_type%22%3A%225%22%2C%22enter_from%22%3A%22click_category%22%2C%22entrance_hotspot%22%3A%22outside%22%2C%22event_type%22%3A%22hot_board%22%2C%22hot_board_cluster_id%22%3A%227150141433956011553%22%2C%22hot_board_impr_id%22%3A%22202210031331410101512050810B60F123%22%2C%22jump_page%22%3A%22hot_board_page%22%2C%22location%22%3A%22news_hot_card%22%2C%22page_location%22%3A%22hot_board_page%22%2C%22rank%22%3A%2232%22%2C%22source%22%3A%22trending_tab%22%2C%22style_id%22%3A%2240132%22%2C%22title%22%3A%22NBA%E5%AD%A3%E5%89%8D%E8%B5%9B%E7%88%86%E5%A4%A7%E5%86%B7%EF%BC%9A%E5%A4%AA%E9%98%B3%E4%B8%8D%E6%95%8CNBL%E9%98%9F%22%7D&rank=32&style_id=40132&topic_id=7150141433956011553","hot":"240053","icon":"https://p26.toutiaoimg.com/img/mosaic-legacy/2b29000041c9b5b3eff94~cs_noop.png","cover":"https://p6.toutiaoimg.com/img/top-static-files-outer/breaknews/13ca84e1-c06e-4a0c-aace-4db4fffab44e~cs_noop.png"},{"title":"北京城中轴线的前世今生","url":"https://www.toutiao.com/amos_land_page/?category_name=topic_innerflow&event_type=hot_board&log_pb=%7B%22category_name%22%3A%22topic_innerflow%22%2C%22cluster_type%22%3A%228%22%2C%22enter_from%22%3A%22click_category%22%2C%22entrance_hotspot%22%3A%22outside%22%2C%22event_type%22%3A%22hot_board%22%2C%22hot_board_cluster_id%22%3A%227149793966177648644%22%2C%22hot_board_impr_id%22%3A%22202210031331410101512050810B60F123%22%2C%22jump_page%22%3A%22hot_board_page%22%2C%22location%22%3A%22news_hot_card%22%2C%22page_location%22%3A%22hot_board_page%22%2C%22rank%22%3A%2233%22%2C%22source%22%3A%22trending_tab%22%2C%22style_id%22%3A%2240132%22%2C%22title%22%3A%22%E5%8C%97%E4%BA%AC%E5%9F%8E%E4%B8%AD%E8%BD%B4%E7%BA%BF%E7%9A%84%E5%89%8D%E4%B8%96%E4%BB%8A%E7%94%9F%22%7D&rank=33&style_id=40132&topic_id=7149793966177648644","hot":"217209","icon":"https://p26.toutiaoimg.com/img/mosaic-legacy/2b29000041c9b5b3eff94~cs_noop.png","cover":"https://p9.toutiaoimg.com/img/mosaic-legacy/2b29000036f8405561443~cs_noop.png"},{"title":"瑞信回应破产传闻：拒绝置评","url":"https://www.toutiao.com/amos_land_page/?category_name=topic_innerflow&event_type=hot_board&log_pb=%7B%22category_name%22%3A%22topic_innerflow%22%2C%22cluster_type%22%3A%226%22%2C%22enter_from%22%3A%22click_category%22%2C%22entrance_hotspot%22%3A%22outside%22%2C%22event_type%22%3A%22hot_board%22%2C%22hot_board_cluster_id%22%3A%227150110218800594974%22%2C%22hot_board_impr_id%22%3A%22202210031331410101512050810B60F123%22%2C%22jump_page%22%3A%22hot_board_page%22%2C%22location%22%3A%22news_hot_card%22%2C%22page_location%22%3A%22hot_board_page%22%2C%22rank%22%3A%2234%22%2C%22source%22%3A%22trending_tab%22%2C%22style_id%22%3A%2240132%22%2C%22title%22%3A%22%E7%91%9E%E4%BF%A1%E5%9B%9E%E5%BA%94%E7%A0%B4%E4%BA%A7%E4%BC%A0%E9%97%BB%EF%BC%9A%E6%8B%92%E7%BB%9D%E7%BD%AE%E8%AF%84%22%7D&rank=34&style_id=40132&topic_id=7150110218800594974","hot":"196539","icon":"","cover":"https://p6.toutiaoimg.com/img/top-static-files-outer/breaknews/8f4e8b46-488f-462d-8502-fa355e631206~cs_noop.png"},{"title":"诺贝尔奖奖金为何越发越多","url":"https://www.toutiao.com/amos_land_page/?category_name=topic_innerflow&event_type=hot_board&log_pb=%7B%22category_name%22%3A%22topic_innerflow%22%2C%22cluster_type%22%3A%221%22%2C%22enter_from%22%3A%22click_category%22%2C%22entrance_hotspot%22%3A%22outside%22%2C%22event_type%22%3A%22hot_board%22%2C%22hot_board_cluster_id%22%3A%227150111613356523535%22%2C%22hot_board_impr_id%22%3A%22202210031331410101512050810B60F123%22%2C%22jump_page%22%3A%22hot_board_page%22%2C%22location%22%3A%22news_hot_card%22%2C%22page_location%22%3A%22hot_board_page%22%2C%22rank%22%3A%2235%22%2C%22source%22%3A%22trending_tab%22%2C%22style_id%22%3A%2240132%22%2C%22title%22%3A%22%E8%AF%BA%E8%B4%9D%E5%B0%94%E5%A5%96%E5%A5%96%E9%87%91%E4%B8%BA%E4%BD%95%E8%B6%8A%E5%8F%91%E8%B6%8A%E5%A4%9A%22%7D&rank=35&style_id=40132&topic_id=7150111613356523535","hot":"177836","icon":"","cover":"https://p26.toutiaoimg.com/img/top-static-files-outer/breaknews/b2339879-1a64-4f44-8f2f-786b6021a1a1~cs_noop.png"},{"title":"余华和残雪成诺贝尔文学奖热门人选","url":"https://www.toutiao.com/amos_land_page/?category_name=topic_innerflow&event_type=hot_board&log_pb=%7B%22category_name%22%3A%22topic_innerflow%22%2C%22cluster_type%22%3A%228%22%2C%22enter_from%22%3A%22click_category%22%2C%22entrance_hotspot%22%3A%22outside%22%2C%22event_type%22%3A%22hot_board%22%2C%22hot_board_cluster_id%22%3A%227149932887813406761%22%2C%22hot_board_impr_id%22%3A%22202210031331410101512050810B60F123%22%2C%22jump_page%22%3A%22hot_board_page%22%2C%22location%22%3A%22news_hot_card%22%2C%22page_location%22%3A%22hot_board_page%22%2C%22rank%22%3A%2236%22%2C%22source%22%3A%22trending_tab%22%2C%22style_id%22%3A%2240132%22%2C%22title%22%3A%22%E4%BD%99%E5%8D%8E%E5%92%8C%E6%AE%8B%E9%9B%AA%E6%88%90%E8%AF%BA%E8%B4%9D%E5%B0%94%E6%96%87%E5%AD%A6%E5%A5%96%E7%83%AD%E9%97%A8%E4%BA%BA%E9%80%89%22%7D&rank=36&style_id=40132&topic_id=7149932887813406761","hot":"160912","icon":"","cover":"https://p26.toutiaoimg.com/img/tos-cn-i-qvj2lq49k0/4cac16786b3040679dbfcfbed7b108ca~cs_noop.png"},{"title":"芬兰总统称未看到俄与西方战争迹象","url":"https://www.toutiao.com/amos_land_page/?category_name=topic_innerflow&event_type=hot_board&log_pb=%7B%22category_name%22%3A%22topic_innerflow%22%2C%22cluster_type%22%3A%226%22%2C%22enter_from%22%3A%22click_category%22%2C%22entrance_hotspot%22%3A%22outside%22%2C%22event_type%22%3A%22hot_board%22%2C%22hot_board_cluster_id%22%3A%227149836885479653389%22%2C%22hot_board_impr_id%22%3A%22202210031331410101512050810B60F123%22%2C%22jump_page%22%3A%22hot_board_page%22%2C%22location%22%3A%22news_hot_card%22%2C%22page_location%22%3A%22hot_board_page%22%2C%22rank%22%3A%2237%22%2C%22source%22%3A%22trending_tab%22%2C%22style_id%22%3A%2240132%22%2C%22title%22%3A%22%E8%8A%AC%E5%85%B0%E6%80%BB%E7%BB%9F%E7%A7%B0%E6%9C%AA%E7%9C%8B%E5%88%B0%E4%BF%84%E4%B8%8E%E8%A5%BF%E6%96%B9%E6%88%98%E4%BA%89%E8%BF%B9%E8%B1%A1%22%7D&rank=37&style_id=40132&topic_id=7149836885479653389","hot":"145599","icon":"","cover":"https://p26.toutiaoimg.com/img/mosaic-legacy/2b29000036f8405561443~cs_noop.png"},{"title":"中国超越德国成世界第二汽车出口国","url":"https://www.toutiao.com/amos_land_page/?category_name=topic_innerflow&event_type=hot_board&log_pb=%7B%22category_name%22%3A%22topic_innerflow%22%2C%22cluster_type%22%3A%226%22%2C%22enter_from%22%3A%22click_category%22%2C%22entrance_hotspot%22%3A%22outside%22%2C%22event_type%22%3A%22hot_board%22%2C%22hot_board_cluster_id%22%3A%227149874764507512847%22%2C%22hot_board_impr_id%22%3A%22202210031331410101512050810B60F123%22%2C%22jump_page%22%3A%22hot_board_page%22%2C%22location%22%3A%22news_hot_card%22%2C%22page_location%22%3A%22hot_board_page%22%2C%22rank%22%3A%2238%22%2C%22source%22%3A%22trending_tab%22%2C%22style_id%22%3A%2240132%22%2C%22title%22%3A%22%E4%B8%AD%E5%9B%BD%E8%B6%85%E8%B6%8A%E5%BE%B7%E5%9B%BD%E6%88%90%E4%B8%96%E7%95%8C%E7%AC%AC%E4%BA%8C%E6%B1%BD%E8%BD%A6%E5%87%BA%E5%8F%A3%E5%9B%BD%22%7D&rank=38&style_id=40132&topic_id=7149874764507512847","hot":"131744","icon":"https://p3.toutiaoimg.com/img/mosaic-legacy/2b29000041c9b5b3eff94~cs_noop.png","cover":"https://p26.toutiaoimg.com/img/top-static-files-outer/breaknews/ee8ffbb7-5359-481e-90e0-52d1b9ccc734~cs_noop.png"},{"title":"酒店民宿“逢假必涨”合法吗","url":"https://www.toutiao.com/amos_land_page/?category_name=topic_innerflow&event_type=hot_board&log_pb=%7B%22category_name%22%3A%22topic_innerflow%22%2C%22cluster_type%22%3A%221%22%2C%22enter_from%22%3A%22click_category%22%2C%22entrance_hotspot%22%3A%22outside%22%2C%22event_type%22%3A%22hot_board%22%2C%22hot_board_cluster_id%22%3A%227150113399622336519%22%2C%22hot_board_impr_id%22%3A%22202210031331410101512050810B60F123%22%2C%22jump_page%22%3A%22hot_board_page%22%2C%22location%22%3A%22news_hot_card%22%2C%22page_location%22%3A%22hot_board_page%22%2C%22rank%22%3A%2239%22%2C%22source%22%3A%22trending_tab%22%2C%22style_id%22%3A%2240132%22%2C%22title%22%3A%22%E9%85%92%E5%BA%97%E6%B0%91%E5%AE%BF%E2%80%9C%E9%80%A2%E5%81%87%E5%BF%85%E6%B6%A8%E2%80%9D%E5%90%88%E6%B3%95%E5%90%97%22%7D&rank=39&style_id=40132&topic_id=7150113399622336519","hot":"119207","icon":"","cover":"https://p3.toutiaoimg.com/img/top-static-files-outer/breaknews/b50cab2e-da70-48fc-ae05-53adfa9c5090~cs_noop.png"},{"title":"女官员被问责2次后再被处理","url":"https://www.toutiao.com/amos_land_page/?category_name=topic_innerflow&event_type=hot_board&log_pb=%7B%22category_name%22%3A%22topic_innerflow%22%2C%22cluster_type%22%3A%220%22%2C%22enter_from%22%3A%22click_category%22%2C%22entrance_hotspot%22%3A%22outside%22%2C%22event_type%22%3A%22hot_board%22%2C%22hot_board_cluster_id%22%3A%227149842205060907039%22%2C%22hot_board_impr_id%22%3A%22202210031331410101512050810B60F123%22%2C%22jump_page%22%3A%22hot_board_page%22%2C%22location%22%3A%22news_hot_card%22%2C%22page_location%22%3A%22hot_board_page%22%2C%22rank%22%3A%2240%22%2C%22source%22%3A%22trending_tab%22%2C%22style_id%22%3A%2240132%22%2C%22title%22%3A%22%E5%A5%B3%E5%AE%98%E5%91%98%E8%A2%AB%E9%97%AE%E8%B4%A32%E6%AC%A1%E5%90%8E%E5%86%8D%E8%A2%AB%E5%A4%84%E7%90%86%22%7D&rank=40&style_id=40132&topic_id=7149842205060907039","hot":"107863","icon":"","cover":"https://p9.toutiaoimg.com/img/tos-cn-i-qvj2lq49k0/b5c939a7deb74f32a72215f35a37953a~cs_noop.png"},{"title":"女篮主帅郑薇：球队需成为真正强队","url":"https://www.toutiao.com/amos_land_page/?category_name=topic_innerflow&event_type=hot_board&log_pb=%7B%22category_name%22%3A%22topic_innerflow%22%2C%22cluster_type%22%3A%220%22%2C%22enter_from%22%3A%22click_category%22%2C%22entrance_hotspot%22%3A%22outside%22%2C%22event_type%22%3A%22hot_board%22%2C%22hot_board_cluster_id%22%3A%227149899789126074380%22%2C%22hot_board_impr_id%22%3A%22202210031331410101512050810B60F123%22%2C%22jump_page%22%3A%22hot_board_page%22%2C%22location%22%3A%22news_hot_card%22%2C%22page_location%22%3A%22hot_board_page%22%2C%22rank%22%3A%2241%22%2C%22source%22%3A%22trending_tab%22%2C%22style_id%22%3A%2240132%22%2C%22title%22%3A%22%E5%A5%B3%E7%AF%AE%E4%B8%BB%E5%B8%85%E9%83%91%E8%96%87%EF%BC%9A%E7%90%83%E9%98%9F%E9%9C%80%E6%88%90%E4%B8%BA%E7%9C%9F%E6%AD%A3%E5%BC%BA%E9%98%9F%22%7D&rank=41&style_id=40132&topic_id=7149899789126074380","hot":"97598","icon":"","cover":"https://p6.toutiaoimg.com/img/top-static-files-outer/breaknews/ae1b9eb0-7c7a-414f-b34d-cda4a4a287b9~cs_noop.png"},{"title":"四川昨增本土45+40","url":"https://www.toutiao.com/amos_land_page/?category_name=topic_innerflow&event_type=hot_board&log_pb=%7B%22category_name%22%3A%22topic_innerflow%22%2C%22cluster_type%22%3A%222%22%2C%22enter_from%22%3A%22click_category%22%2C%22entrance_hotspot%22%3A%22outside%22%2C%22event_type%22%3A%22hot_board%22%2C%22hot_board_cluster_id%22%3A%227149921264017080356%22%2C%22hot_board_impr_id%22%3A%22202210031331410101512050810B60F123%22%2C%22jump_page%22%3A%22hot_board_page%22%2C%22location%22%3A%22news_hot_card%22%2C%22page_location%22%3A%22hot_board_page%22%2C%22rank%22%3A%2242%22%2C%22source%22%3A%22trending_tab%22%2C%22style_id%22%3A%2240132%22%2C%22title%22%3A%22%E5%9B%9B%E5%B7%9D%E6%98%A8%E5%A2%9E%E6%9C%AC%E5%9C%9F45%2B40%22%7D&rank=42&style_id=40132&topic_id=7149921264017080356","hot":"88310","icon":"","cover":"https://p26.toutiaoimg.com/img/top-static-files-outer/breaknews/9cb0a082-e262-4b72-9cfc-05062d023a87~cs_noop.png"},{"title":"老人气球挂路杆 奔驰车主找叉车帮忙","url":"https://www.toutiao.com/amos_land_page/?category_name=topic_innerflow&event_type=hot_board&log_pb=%7B%22category_name%22%3A%22topic_innerflow%22%2C%22cluster_type%22%3A%222%22%2C%22enter_from%22%3A%22click_category%22%2C%22entrance_hotspot%22%3A%22outside%22%2C%22event_type%22%3A%22hot_board%22%2C%22hot_board_cluster_id%22%3A%227149507251945799710%22%2C%22hot_board_impr_id%22%3A%22202210031331410101512050810B60F123%22%2C%22jump_page%22%3A%22hot_board_page%22%2C%22location%22%3A%22news_hot_card%22%2C%22page_location%22%3A%22hot_board_page%22%2C%22rank%22%3A%2243%22%2C%22source%22%3A%22trending_tab%22%2C%22style_id%22%3A%2240132%22%2C%22title%22%3A%22%E8%80%81%E4%BA%BA%E6%B0%94%E7%90%83%E6%8C%82%E8%B7%AF%E6%9D%86+%E5%A5%94%E9%A9%B0%E8%BD%A6%E4%B8%BB%E6%89%BE%E5%8F%89%E8%BD%A6%E5%B8%AE%E5%BF%99%22%7D&rank=43&style_id=40132&topic_id=7149507251945799710","hot":"79906","icon":"https://p3.toutiaoimg.com/img/mosaic-legacy/2b29000041c9b5b3eff94~cs_noop.png","cover":"https://p5-testdcdn.itoutiaoimg.com/img/mosaic-legacy/2b29000036f8405561443~cs_noop.png"},{"title":"四车拆解：变速箱首切CVT磨损严重","url":"https://www.toutiao.com/amos_land_page/?category_name=topic_innerflow&event_type=hot_board&log_pb=%7B%22category_name%22%3A%22topic_innerflow%22%2C%22cluster_type%22%3A%221%22%2C%22enter_from%22%3A%22click_category%22%2C%22entrance_hotspot%22%3A%22outside%22%2C%22event_type%22%3A%22hot_board%22%2C%22hot_board_cluster_id%22%3A%227149377792218513422%22%2C%22hot_board_impr_id%22%3A%22202210031331410101512050810B60F123%22%2C%22jump_page%22%3A%22hot_board_page%22%2C%22location%22%3A%22news_hot_card%22%2C%22page_location%22%3A%22hot_board_page%22%2C%22rank%22%3A%2244%22%2C%22source%22%3A%22trending_tab%22%2C%22style_id%22%3A%2240132%22%2C%22title%22%3A%22%E5%9B%9B%E8%BD%A6%E6%8B%86%E8%A7%A3%EF%BC%9A%E5%8F%98%E9%80%9F%E7%AE%B1%E9%A6%96%E5%88%87CVT%E7%A3%A8%E6%8D%9F%E4%B8%A5%E9%87%8D%22%7D&rank=44&style_id=40132&topic_id=7149377792218513422","hot":"72302","icon":"","cover":"https://p3.toutiaoimg.com/img/tos-cn-i-qvj2lq49k0/c260439b9f114d1cac24097eeec828ad~cs_noop.png"},{"title":"夜爬泰山遇暴雨 网友调侃“历劫”","url":"https://www.toutiao.com/amos_land_page/?category_name=topic_innerflow&event_type=hot_board&log_pb=%7B%22category_name%22%3A%22topic_innerflow%22%2C%22cluster_type%22%3A%222%22%2C%22enter_from%22%3A%22click_category%22%2C%22entrance_hotspot%22%3A%22outside%22%2C%22event_type%22%3A%22hot_board%22%2C%22hot_board_cluster_id%22%3A%227150105171639402503%22%2C%22hot_board_impr_id%22%3A%22202210031331410101512050810B60F123%22%2C%22jump_page%22%3A%22hot_board_page%22%2C%22location%22%3A%22news_hot_card%22%2C%22page_location%22%3A%22hot_board_page%22%2C%22rank%22%3A%2245%22%2C%22source%22%3A%22trending_tab%22%2C%22style_id%22%3A%2240132%22%2C%22title%22%3A%22%E5%A4%9C%E7%88%AC%E6%B3%B0%E5%B1%B1%E9%81%87%E6%9A%B4%E9%9B%A8+%E7%BD%91%E5%8F%8B%E8%B0%83%E4%BE%83%E2%80%9C%E5%8E%86%E5%8A%AB%E2%80%9D%22%7D&rank=45&style_id=40132&topic_id=7150105171639402503","hot":"65422","icon":"https://p26.toutiaoimg.com/img/mosaic-legacy/2b29000041c9b5b3eff94~cs_noop.png","cover":"https://p3.toutiaoimg.com/img/mosaic-legacy/2b29000036f8405561443~cs_noop.png"},{"title":"特斯拉堵车耗尽电 加价2000叫拖车","url":"https://www.toutiao.com/amos_land_page/?category_name=topic_innerflow&event_type=hot_board&log_pb=%7B%22category_name%22%3A%22topic_innerflow%22%2C%22cluster_type%22%3A%220%22%2C%22enter_from%22%3A%22click_category%22%2C%22entrance_hotspot%22%3A%22outside%22%2C%22event_type%22%3A%22hot_board%22%2C%22hot_board_cluster_id%22%3A%227149958344369930240%22%2C%22hot_board_impr_id%22%3A%22202210031331410101512050810B60F123%22%2C%22jump_page%22%3A%22hot_board_page%22%2C%22location%22%3A%22news_hot_card%22%2C%22page_location%22%3A%22hot_board_page%22%2C%22rank%22%3A%2246%22%2C%22source%22%3A%22trending_tab%22%2C%22style_id%22%3A%2240132%22%2C%22title%22%3A%22%E7%89%B9%E6%96%AF%E6%8B%89%E5%A0%B5%E8%BD%A6%E8%80%97%E5%B0%BD%E7%94%B5+%E5%8A%A0%E4%BB%B72000%E5%8F%AB%E6%8B%96%E8%BD%A6%22%7D&rank=46&style_id=40132&topic_id=7149958344369930240","hot":"59196","icon":"https://p26.toutiaoimg.com/img/mosaic-legacy/2b29000041c9b5b3eff94~cs_noop.png","cover":"https://p6.toutiaoimg.com/img/mosaic-legacy/2b29000036f8405561443~cs_noop.png"},{"title":"英媒称特拉斯反对国王出席气候大会","url":"https://www.toutiao.com/amos_land_page/?category_name=topic_innerflow&event_type=hot_board&log_pb=%7B%22category_name%22%3A%22topic_innerflow%22%2C%22cluster_type%22%3A%226%22%2C%22enter_from%22%3A%22click_category%22%2C%22entrance_hotspot%22%3A%22outside%22%2C%22event_type%22%3A%22hot_board%22%2C%22hot_board_cluster_id%22%3A%227149672220535554060%22%2C%22hot_board_impr_id%22%3A%22202210031331410101512050810B60F123%22%2C%22jump_page%22%3A%22hot_board_page%22%2C%22location%22%3A%22news_hot_card%22%2C%22page_location%22%3A%22hot_board_page%22%2C%22rank%22%3A%2247%22%2C%22source%22%3A%22trending_tab%22%2C%22style_id%22%3A%2240132%22%2C%22title%22%3A%22%E8%8B%B1%E5%AA%92%E7%A7%B0%E7%89%B9%E6%8B%89%E6%96%AF%E5%8F%8D%E5%AF%B9%E5%9B%BD%E7%8E%8B%E5%87%BA%E5%B8%AD%E6%B0%94%E5%80%99%E5%A4%A7%E4%BC%9A%22%7D&rank=47&style_id=40132&topic_id=7149672220535554060","hot":"53563","icon":"","cover":"https://p6.toutiaoimg.com/img/tos-cn-i-qvj2lq49k0/d4895dff9e18485d9bb4ecdf119a4240~cs_noop.png"},{"title":"普京将任命顿涅茨克等地代理领导人","url":"https://www.toutiao.com/amos_land_page/?category_name=topic_innerflow&event_type=hot_board&log_pb=%7B%22category_name%22%3A%22topic_innerflow%22%2C%22cluster_type%22%3A%226%22%2C%22enter_from%22%3A%22click_category%22%2C%22entrance_hotspot%22%3A%22outside%22%2C%22event_type%22%3A%22hot_board%22%2C%22hot_board_cluster_id%22%3A%227150106866142412812%22%2C%22hot_board_impr_id%22%3A%22202210031331410101512050810B60F123%22%2C%22jump_page%22%3A%22hot_board_page%22%2C%22location%22%3A%22news_hot_card%22%2C%22page_location%22%3A%22hot_board_page%22%2C%22rank%22%3A%2248%22%2C%22source%22%3A%22trending_tab%22%2C%22style_id%22%3A%2240132%22%2C%22title%22%3A%22%E6%99%AE%E4%BA%AC%E5%B0%86%E4%BB%BB%E5%91%BD%E9%A1%BF%E6%B6%85%E8%8C%A8%E5%85%8B%E7%AD%89%E5%9C%B0%E4%BB%A3%E7%90%86%E9%A2%86%E5%AF%BC%E4%BA%BA%22%7D&rank=48&style_id=40132&topic_id=7150106866142412812","hot":"48465","icon":"","cover":"https://p26.toutiaoimg.com/img/top-static-files-outer/breaknews/29c53115-804c-4f68-a21e-43d7cbb1ade7~cs_noop.png"},{"title":"法媒曝法国将再向乌提供自行火炮","url":"https://www.toutiao.com/amos_land_page/?category_name=topic_innerflow&event_type=hot_board&log_pb=%7B%22category_name%22%3A%22topic_innerflow%22%2C%22cluster_type%22%3A%226%22%2C%22enter_from%22%3A%22click_category%22%2C%22entrance_hotspot%22%3A%22outside%22%2C%22event_type%22%3A%22hot_board%22%2C%22hot_board_cluster_id%22%3A%227150000213761982472%22%2C%22hot_board_impr_id%22%3A%22202210031331410101512050810B60F123%22%2C%22jump_page%22%3A%22hot_board_page%22%2C%22location%22%3A%22news_hot_card%22%2C%22page_location%22%3A%22hot_board_page%22%2C%22rank%22%3A%2249%22%2C%22source%22%3A%22trending_tab%22%2C%22style_id%22%3A%2240132%22%2C%22title%22%3A%22%E6%B3%95%E5%AA%92%E6%9B%9D%E6%B3%95%E5%9B%BD%E5%B0%86%E5%86%8D%E5%90%91%E4%B9%8C%E6%8F%90%E4%BE%9B%E8%87%AA%E8%A1%8C%E7%81%AB%E7%82%AE%22%7D&rank=49&style_id=40132&topic_id=7150000213761982472","hot":"43853","icon":"","cover":"https://p26.toutiaoimg.com/img/top-static-files-outer/breaknews/6a59d265-ae66-4050-ab1d-9ad25a7dc1da~cs_noop.png"},{"title":"巴基斯坦洪灾已造成近1700人死亡","url":"https://www.toutiao.com/amos_land_page/?category_name=topic_innerflow&event_type=hot_board&log_pb=%7B%22category_name%22%3A%22topic_innerflow%22%2C%22cluster_type%22%3A%226%22%2C%22enter_from%22%3A%22click_category%22%2C%22entrance_hotspot%22%3A%22outside%22%2C%22event_type%22%3A%22hot_board%22%2C%22hot_board_cluster_id%22%3A%227150100577949581353%22%2C%22hot_board_impr_id%22%3A%22202210031331410101512050810B60F123%22%2C%22jump_page%22%3A%22hot_board_page%22%2C%22location%22%3A%22news_hot_card%22%2C%22page_location%22%3A%22hot_board_page%22%2C%22rank%22%3A%2250%22%2C%22source%22%3A%22trending_tab%22%2C%22style_id%22%3A%2240132%22%2C%22title%22%3A%22%E5%B7%B4%E5%9F%BA%E6%96%AF%E5%9D%A6%E6%B4%AA%E7%81%BE%E5%B7%B2%E9%80%A0%E6%88%90%E8%BF%911700%E4%BA%BA%E6%AD%BB%E4%BA%A1%22%7D&rank=50&style_id=40132&topic_id=7150100577949581353","hot":"39680","icon":"","cover":"https://p9.toutiaoimg.com/img/tos-cn-i-qvj2lq49k0/4791044fc12e481293dafef9cc1d00f8~cs_noop.png"}]