[{"title":"平顶山巨型怪鱼系高危外来生物","url":"https://www.toutiao.com/amos_land_page/?category_name=topic_innerflow&event_type=hot_board&log_pb=%7B%22category_name%22%3A%22topic_innerflow%22%2C%22cluster_type%22%3A%222%22%2C%22enter_from%22%3A%22click_category%22%2C%22entrance_hotspot%22%3A%22outside%22%2C%22event_type%22%3A%22hot_board%22%2C%22hot_board_cluster_id%22%3A%227134296279235952673%22%2C%22hot_board_impr_id%22%3A%2220220824054117010135119019165D8022%22%2C%22jump_page%22%3A%22hot_board_page%22%2C%22location%22%3A%22news_hot_card%22%2C%22page_location%22%3A%22hot_board_page%22%2C%22rank%22%3A%221%22%2C%22source%22%3A%22trending_tab%22%2C%22style_id%22%3A%2240132%22%2C%22title%22%3A%22%E5%B9%B3%E9%A1%B6%E5%B1%B1%E5%B7%A8%E5%9E%8B%E6%80%AA%E9%B1%BC%E7%B3%BB%E9%AB%98%E5%8D%B1%E5%A4%96%E6%9D%A5%E7%94%9F%E7%89%A9%22%7D&rank=1&style_id=40132&topic_id=7134296279235952673","hot":"9492679","icon":"https://p6.toutiaoimg.com/img/mosaic-legacy/2b29200041b9c651e8148~cs_noop.png","cover":"https://p26.toutiaoimg.com/img/tos-cn-i-qvj2lq49k0/85f9a5c5e49144679b5467164ed2221d~cs_noop.png"},{"title":"日本国会议员窜台 中方将采取措施","url":"https://www.toutiao.com/amos_land_page/?category_name=topic_innerflow&event_type=hot_board&log_pb=%7B%22category_name%22%3A%22topic_innerflow%22%2C%22cluster_type%22%3A%222%22%2C%22enter_from%22%3A%22click_category%22%2C%22entrance_hotspot%22%3A%22outside%22%2C%22event_type%22%3A%22hot_board%22%2C%22hot_board_cluster_id%22%3A%227130222756762783268%22%2C%22hot_board_impr_id%22%3A%2220220824054117010135119019165D8022%22%2C%22jump_page%22%3A%22hot_board_page%22%2C%22location%22%3A%22news_hot_card%22%2C%22page_location%22%3A%22hot_board_page%22%2C%22rank%22%3A%222%22%2C%22source%22%3A%22trending_tab%22%2C%22style_id%22%3A%2240132%22%2C%22title%22%3A%22%E6%97%A5%E6%9C%AC%E5%9B%BD%E4%BC%9A%E8%AE%AE%E5%91%98%E7%AA%9C%E5%8F%B0+%E4%B8%AD%E6%96%B9%E5%B0%86%E9%87%87%E5%8F%96%E6%8E%AA%E6%96%BD%22%7D&rank=2&style_id=40132&topic_id=7130222756762783268","hot":"8589332","icon":"https://p3.toutiaoimg.com/img/mosaic-legacy/2b29200041b9c651e8148~cs_noop.png","cover":"https://p26.toutiaoimg.com/img/top-static-files-outer/breaknews/9431a770-35be-4863-95ae-fa5e71f90787~cs_noop.png"},{"title":"全力做好各项救灾救助工作","url":"https://www.toutiao.com/amos_land_page/?category_name=topic_innerflow&event_type=hot_board&log_pb=%7B%22category_name%22%3A%22topic_innerflow%22%2C%22cluster_type%22%3A%222%22%2C%22enter_from%22%3A%22click_category%22%2C%22entrance_hotspot%22%3A%22outside%22%2C%22event_type%22%3A%22hot_board%22%2C%22hot_board_cluster_id%22%3A%227134236348742893580%22%2C%22hot_board_impr_id%22%3A%2220220824054117010135119019165D8022%22%2C%22jump_page%22%3A%22hot_board_page%22%2C%22location%22%3A%22news_hot_card%22%2C%22page_location%22%3A%22hot_board_page%22%2C%22rank%22%3A%223%22%2C%22source%22%3A%22trending_tab%22%2C%22style_id%22%3A%2240132%22%2C%22title%22%3A%22%E5%85%A8%E5%8A%9B%E5%81%9A%E5%A5%BD%E5%90%84%E9%A1%B9%E6%95%91%E7%81%BE%E6%95%91%E5%8A%A9%E5%B7%A5%E4%BD%9C%22%7D&rank=3&style_id=40132&topic_id=7134236348742893580","hot":"7771948","icon":"","cover":"https://p9.toutiaoimg.com/img/mosaic-legacy/2b29000036f8405561443~cs_noop.png"},{"title":"俄方公布杜金娜遇害案嫌犯画面","url":"https://www.toutiao.com/amos_land_page/?category_name=topic_innerflow&event_type=hot_board&log_pb=%7B%22category_name%22%3A%22topic_innerflow%22%2C%22cluster_type%22%3A%222%22%2C%22enter_from%22%3A%22click_category%22%2C%22entrance_hotspot%22%3A%22outside%22%2C%22event_type%22%3A%22hot_board%22%2C%22hot_board_cluster_id%22%3A%227134731587375562793%22%2C%22hot_board_impr_id%22%3A%2220220824054117010135119019165D8022%22%2C%22jump_page%22%3A%22hot_board_page%22%2C%22location%22%3A%22news_hot_card%22%2C%22page_location%22%3A%22hot_board_page%22%2C%22rank%22%3A%224%22%2C%22source%22%3A%22trending_tab%22%2C%22style_id%22%3A%2240132%22%2C%22title%22%3A%22%E4%BF%84%E6%96%B9%E5%85%AC%E5%B8%83%E6%9D%9C%E9%87%91%E5%A8%9C%E9%81%87%E5%AE%B3%E6%A1%88%E5%AB%8C%E7%8A%AF%E7%94%BB%E9%9D%A2%22%7D&rank=4&style_id=40132&topic_id=7134731587375562793","hot":"7032350","icon":"https://p3.toutiaoimg.com/img/mosaic-legacy/2b29200041b9c651e8148~cs_noop.png","cover":"https://p26.toutiaoimg.com/img/tos-cn-i-qvj2lq49k0/4414d12144134f57bd31bd1d781960bc~cs_noop.png"},{"title":"台前官员怒告蔡英文通美挑衅大陆","url":"https://www.toutiao.com/amos_land_page/?category_name=topic_innerflow&event_type=hot_board&log_pb=%7B%22category_name%22%3A%22topic_innerflow%22%2C%22cluster_type%22%3A%220%22%2C%22enter_from%22%3A%22click_category%22%2C%22entrance_hotspot%22%3A%22outside%22%2C%22event_type%22%3A%22hot_board%22%2C%22hot_board_cluster_id%22%3A%227134616223672696867%22%2C%22hot_board_impr_id%22%3A%2220220824054117010135119019165D8022%22%2C%22jump_page%22%3A%22hot_board_page%22%2C%22location%22%3A%22news_hot_card%22%2C%22page_location%22%3A%22hot_board_page%22%2C%22rank%22%3A%225%22%2C%22source%22%3A%22trending_tab%22%2C%22style_id%22%3A%2240132%22%2C%22title%22%3A%22%E5%8F%B0%E5%89%8D%E5%AE%98%E5%91%98%E6%80%92%E5%91%8A%E8%94%A1%E8%8B%B1%E6%96%87%E9%80%9A%E7%BE%8E%E6%8C%91%E8%A1%85%E5%A4%A7%E9%99%86%22%7D&rank=5&style_id=40132&topic_id=7134616223672696867","hot":"6363133","icon":"","cover":"https://p26.toutiaoimg.com/img/top-static-files-outer/breaknews/d39ec203-cd13-4ec5-9dfc-fae7834663fe~cs_noop.png"},{"title":"律师：湘雅医生刘翔峰或涉故意伤害","url":"https://www.toutiao.com/amos_land_page/?category_name=topic_innerflow&event_type=hot_board&log_pb=%7B%22category_name%22%3A%22topic_innerflow%22%2C%22cluster_type%22%3A%221%22%2C%22enter_from%22%3A%22click_category%22%2C%22entrance_hotspot%22%3A%22outside%22%2C%22event_type%22%3A%22hot_board%22%2C%22hot_board_cluster_id%22%3A%227134728374831808552%22%2C%22hot_board_impr_id%22%3A%2220220824054117010135119019165D8022%22%2C%22jump_page%22%3A%22hot_board_page%22%2C%22location%22%3A%22news_hot_card%22%2C%22page_location%22%3A%22hot_board_page%22%2C%22rank%22%3A%226%22%2C%22source%22%3A%22trending_tab%22%2C%22style_id%22%3A%2240132%22%2C%22title%22%3A%22%E5%BE%8B%E5%B8%88%EF%BC%9A%E6%B9%98%E9%9B%85%E5%8C%BB%E7%94%9F%E5%88%98%E7%BF%94%E5%B3%B0%E6%88%96%E6%B6%89%E6%95%85%E6%84%8F%E4%BC%A4%E5%AE%B3%22%7D&rank=6&style_id=40132&topic_id=7134728374831808552","hot":"5757601","icon":"","cover":"https://p26.toutiaoimg.com/img/top-static-files-outer/breaknews/2616cb2f-75b4-4b82-ba74-d2d54f28dc6a~cs_noop.png"},{"title":"美国就杜金娜案发声：不提供评估","url":"https://www.toutiao.com/amos_land_page/?category_name=topic_innerflow&event_type=hot_board&log_pb=%7B%22category_name%22%3A%22topic_innerflow%22%2C%22cluster_type%22%3A%226%22%2C%22enter_from%22%3A%22click_category%22%2C%22entrance_hotspot%22%3A%22outside%22%2C%22event_type%22%3A%22hot_board%22%2C%22hot_board_cluster_id%22%3A%227134890337159348231%22%2C%22hot_board_impr_id%22%3A%2220220824054117010135119019165D8022%22%2C%22jump_page%22%3A%22hot_board_page%22%2C%22location%22%3A%22news_hot_card%22%2C%22page_location%22%3A%22hot_board_page%22%2C%22rank%22%3A%227%22%2C%22source%22%3A%22trending_tab%22%2C%22style_id%22%3A%2240132%22%2C%22title%22%3A%22%E7%BE%8E%E5%9B%BD%E5%B0%B1%E6%9D%9C%E9%87%91%E5%A8%9C%E6%A1%88%E5%8F%91%E5%A3%B0%EF%BC%9A%E4%B8%8D%E6%8F%90%E4%BE%9B%E8%AF%84%E4%BC%B0%22%7D&rank=7&style_id=40132&topic_id=7134890337159348231","hot":"5209693","icon":"","cover":"https://p26.toutiaoimg.com/img/tos-cn-i-qvj2lq49k0/9068f64a24814180a3f58c604659bfb2~cs_noop.png"},{"title":"无印良品在中国9年降价11次","url":"https://www.toutiao.com/amos_land_page/?category_name=topic_innerflow&event_type=hot_board&log_pb=%7B%22category_name%22%3A%22topic_innerflow%22%2C%22cluster_type%22%3A%228%22%2C%22enter_from%22%3A%22click_category%22%2C%22entrance_hotspot%22%3A%22outside%22%2C%22event_type%22%3A%22hot_board%22%2C%22hot_board_cluster_id%22%3A%227134378350285422605%22%2C%22hot_board_impr_id%22%3A%2220220824054117010135119019165D8022%22%2C%22jump_page%22%3A%22hot_board_page%22%2C%22location%22%3A%22news_hot_card%22%2C%22page_location%22%3A%22hot_board_page%22%2C%22rank%22%3A%228%22%2C%22source%22%3A%22trending_tab%22%2C%22style_id%22%3A%2240132%22%2C%22title%22%3A%22%E6%97%A0%E5%8D%B0%E8%89%AF%E5%93%81%E5%9C%A8%E4%B8%AD%E5%9B%BD9%E5%B9%B4%E9%99%8D%E4%BB%B711%E6%AC%A1%22%7D&rank=8&style_id=40132&topic_id=7134378350285422605","hot":"4713925","icon":"","cover":"https://p26.toutiaoimg.com/img/tos-cn-i-qvj2lq49k0/129d66ca08264e4d85381ec46b0ef8c3~cs_noop.png"},{"title":"15岁少年坐公交旅行：4天9城花153元","url":"https://www.toutiao.com/amos_land_page/?category_name=topic_innerflow&event_type=hot_board&log_pb=%7B%22category_name%22%3A%22topic_innerflow%22%2C%22cluster_type%22%3A%222%22%2C%22enter_from%22%3A%22click_category%22%2C%22entrance_hotspot%22%3A%22outside%22%2C%22event_type%22%3A%22hot_board%22%2C%22hot_board_cluster_id%22%3A%227134687644516089856%22%2C%22hot_board_impr_id%22%3A%2220220824054117010135119019165D8022%22%2C%22jump_page%22%3A%22hot_board_page%22%2C%22location%22%3A%22news_hot_card%22%2C%22page_location%22%3A%22hot_board_page%22%2C%22rank%22%3A%229%22%2C%22source%22%3A%22trending_tab%22%2C%22style_id%22%3A%2240132%22%2C%22title%22%3A%2215%E5%B2%81%E5%B0%91%E5%B9%B4%E5%9D%90%E5%85%AC%E4%BA%A4%E6%97%85%E8%A1%8C%EF%BC%9A4%E5%A4%A99%E5%9F%8E%E8%8A%B1153%E5%85%83%22%7D&rank=9&style_id=40132&topic_id=7134687644516089856","hot":"4265336","icon":"","cover":"https://p9.toutiaoimg.com/img/top-static-files-outer/breaknews/eff6d4d2-37c7-4421-b195-299a71495a7d~cs_noop.png"},{"title":"法国电视台就嘉宾做辱华动作道歉","url":"https://www.toutiao.com/amos_land_page/?category_name=topic_innerflow&event_type=hot_board&log_pb=%7B%22category_name%22%3A%22topic_innerflow%22%2C%22cluster_type%22%3A%226%22%2C%22enter_from%22%3A%22click_category%22%2C%22entrance_hotspot%22%3A%22outside%22%2C%22event_type%22%3A%22hot_board%22%2C%22hot_board_cluster_id%22%3A%227134618308115955715%22%2C%22hot_board_impr_id%22%3A%2220220824054117010135119019165D8022%22%2C%22jump_page%22%3A%22hot_board_page%22%2C%22location%22%3A%22news_hot_card%22%2C%22page_location%22%3A%22hot_board_page%22%2C%22rank%22%3A%2210%22%2C%22source%22%3A%22trending_tab%22%2C%22style_id%22%3A%2240132%22%2C%22title%22%3A%22%E6%B3%95%E5%9B%BD%E7%94%B5%E8%A7%86%E5%8F%B0%E5%B0%B1%E5%98%89%E5%AE%BE%E5%81%9A%E8%BE%B1%E5%8D%8E%E5%8A%A8%E4%BD%9C%E9%81%93%E6%AD%89%22%7D&rank=10&style_id=40132&topic_id=7134618308115955715","hot":"3859435","icon":"","cover":"https://p6.toutiaoimg.com/img/top-static-files-outer/breaknews/0e58e3a7-3613-4dff-9013-d60107d08d2f~cs_noop.png"},{"title":"老人组团偷南瓜 律师：不拘留可罚款","url":"https://www.toutiao.com/amos_land_page/?category_name=topic_innerflow&event_type=hot_board&log_pb=%7B%22category_name%22%3A%22topic_innerflow%22%2C%22cluster_type%22%3A%221%22%2C%22enter_from%22%3A%22click_category%22%2C%22entrance_hotspot%22%3A%22outside%22%2C%22event_type%22%3A%22hot_board%22%2C%22hot_board_cluster_id%22%3A%227134314923349245964%22%2C%22hot_board_impr_id%22%3A%2220220824054117010135119019165D8022%22%2C%22jump_page%22%3A%22hot_board_page%22%2C%22location%22%3A%22news_hot_card%22%2C%22page_location%22%3A%22hot_board_page%22%2C%22rank%22%3A%2211%22%2C%22source%22%3A%22trending_tab%22%2C%22style_id%22%3A%2240132%22%2C%22title%22%3A%22%E8%80%81%E4%BA%BA%E7%BB%84%E5%9B%A2%E5%81%B7%E5%8D%97%E7%93%9C+%E5%BE%8B%E5%B8%88%EF%BC%9A%E4%B8%8D%E6%8B%98%E7%95%99%E5%8F%AF%E7%BD%9A%E6%AC%BE%22%7D&rank=11&style_id=40132&topic_id=7134314923349245964","hot":"3492161","icon":"","cover":"https://p9.toutiaoimg.com/img/top-static-files-outer/breaknews/31dab2ae-b411-45a1-8845-fbbefa8afe41~cs_noop.png"},{"title":"美国驻乌大使馆敦促美公民立即离乌","url":"https://www.toutiao.com/amos_land_page/?category_name=topic_innerflow&event_type=hot_board&log_pb=%7B%22category_name%22%3A%22topic_innerflow%22%2C%22cluster_type%22%3A%226%22%2C%22enter_from%22%3A%22click_category%22%2C%22entrance_hotspot%22%3A%22outside%22%2C%22event_type%22%3A%22hot_board%22%2C%22hot_board_cluster_id%22%3A%227134924255405768704%22%2C%22hot_board_impr_id%22%3A%2220220824054117010135119019165D8022%22%2C%22jump_page%22%3A%22hot_board_page%22%2C%22location%22%3A%22news_hot_card%22%2C%22page_location%22%3A%22hot_board_page%22%2C%22rank%22%3A%2212%22%2C%22source%22%3A%22trending_tab%22%2C%22style_id%22%3A%2240132%22%2C%22title%22%3A%22%E7%BE%8E%E5%9B%BD%E9%A9%BB%E4%B9%8C%E5%A4%A7%E4%BD%BF%E9%A6%86%E6%95%A6%E4%BF%83%E7%BE%8E%E5%85%AC%E6%B0%91%E7%AB%8B%E5%8D%B3%E7%A6%BB%E4%B9%8C%22%7D&rank=12&style_id=40132&topic_id=7134924255405768704","hot":"3159838","icon":"","cover":"https://p6.toutiaoimg.com/img/top-static-files-outer/breaknews/cecffcb5-4ab4-4d43-b1ed-67659c861713~cs_noop.png"},{"title":"鄱阳湖干枯水域：渔民湖上骑车","url":"https://www.toutiao.com/amos_land_page/?category_name=topic_innerflow&event_type=hot_board&log_pb=%7B%22category_name%22%3A%22topic_innerflow%22%2C%22cluster_type%22%3A%220%22%2C%22enter_from%22%3A%22click_category%22%2C%22entrance_hotspot%22%3A%22outside%22%2C%22event_type%22%3A%22hot_board%22%2C%22hot_board_cluster_id%22%3A%227134899940156932129%22%2C%22hot_board_impr_id%22%3A%2220220824054117010135119019165D8022%22%2C%22jump_page%22%3A%22hot_board_page%22%2C%22location%22%3A%22news_hot_card%22%2C%22page_location%22%3A%22hot_board_page%22%2C%22rank%22%3A%2213%22%2C%22source%22%3A%22trending_tab%22%2C%22style_id%22%3A%2240132%22%2C%22title%22%3A%22%E9%84%B1%E9%98%B3%E6%B9%96%E5%B9%B2%E6%9E%AF%E6%B0%B4%E5%9F%9F%EF%BC%9A%E6%B8%94%E6%B0%91%E6%B9%96%E4%B8%8A%E9%AA%91%E8%BD%A6%22%7D&rank=13&style_id=40132&topic_id=7134899940156932129","hot":"2859140","icon":"","cover":"https://p9.toutiaoimg.com/img/tos-cn-i-qvj2lq49k0/7b0e2f042c13434590b4fb41cf6be3d2~cs_noop.png"},{"title":"美制“死神”无人机在利比亚被击落","url":"https://www.toutiao.com/amos_land_page/?category_name=topic_innerflow&event_type=hot_board&log_pb=%7B%22category_name%22%3A%22topic_innerflow%22%2C%22cluster_type%22%3A%226%22%2C%22enter_from%22%3A%22click_category%22%2C%22entrance_hotspot%22%3A%22outside%22%2C%22event_type%22%3A%22hot_board%22%2C%22hot_board_cluster_id%22%3A%227134887432100511758%22%2C%22hot_board_impr_id%22%3A%2220220824054117010135119019165D8022%22%2C%22jump_page%22%3A%22hot_board_page%22%2C%22location%22%3A%22news_hot_card%22%2C%22page_location%22%3A%22hot_board_page%22%2C%22rank%22%3A%2214%22%2C%22source%22%3A%22trending_tab%22%2C%22style_id%22%3A%2240132%22%2C%22title%22%3A%22%E7%BE%8E%E5%88%B6%E2%80%9C%E6%AD%BB%E7%A5%9E%E2%80%9D%E6%97%A0%E4%BA%BA%E6%9C%BA%E5%9C%A8%E5%88%A9%E6%AF%94%E4%BA%9A%E8%A2%AB%E5%87%BB%E8%90%BD%22%7D&rank=14&style_id=40132&topic_id=7134887432100511758","hot":"2587057","icon":"","cover":"https://p6.toutiaoimg.com/img/top-static-files-outer/breaknews/17d77280-a12b-431a-835d-01c8ae0b9e73~cs_noop.png"},{"title":"药神父亲这一年：为儿子再挣一次命","url":"https://www.toutiao.com/amos_land_page/?category_name=topic_innerflow&event_type=hot_board&log_pb=%7B%22category_name%22%3A%22topic_innerflow%22%2C%22cluster_type%22%3A%221%22%2C%22enter_from%22%3A%22click_category%22%2C%22entrance_hotspot%22%3A%22outside%22%2C%22event_type%22%3A%22hot_board%22%2C%22hot_board_cluster_id%22%3A%227134932560148168737%22%2C%22hot_board_impr_id%22%3A%2220220824054117010135119019165D8022%22%2C%22jump_page%22%3A%22hot_board_page%22%2C%22location%22%3A%22news_hot_card%22%2C%22page_location%22%3A%22hot_board_page%22%2C%22rank%22%3A%2215%22%2C%22source%22%3A%22trending_tab%22%2C%22style_id%22%3A%2240132%22%2C%22title%22%3A%22%E8%8D%AF%E7%A5%9E%E7%88%B6%E4%BA%B2%E8%BF%99%E4%B8%80%E5%B9%B4%EF%BC%9A%E4%B8%BA%E5%84%BF%E5%AD%90%E5%86%8D%E6%8C%A3%E4%B8%80%E6%AC%A1%E5%91%BD%22%7D&rank=15&style_id=40132&topic_id=7134932560148168737","hot":"2340866","icon":"","cover":"https://p3.toutiaoimg.com/img/tos-cn-i-qvj2lq49k0/09bef68b8cc341069b1f654152272055~cs_noop.png"},{"title":"男子凌晨擅自进合租女子房间被拘","url":"https://www.toutiao.com/amos_land_page/?category_name=topic_innerflow&event_type=hot_board&log_pb=%7B%22category_name%22%3A%22topic_innerflow%22%2C%22cluster_type%22%3A%220%22%2C%22enter_from%22%3A%22click_category%22%2C%22entrance_hotspot%22%3A%22outside%22%2C%22event_type%22%3A%22hot_board%22%2C%22hot_board_cluster_id%22%3A%227134984122031669279%22%2C%22hot_board_impr_id%22%3A%2220220824054117010135119019165D8022%22%2C%22jump_page%22%3A%22hot_board_page%22%2C%22location%22%3A%22news_hot_card%22%2C%22page_location%22%3A%22hot_board_page%22%2C%22rank%22%3A%2216%22%2C%22source%22%3A%22trending_tab%22%2C%22style_id%22%3A%2240132%22%2C%22title%22%3A%22%E7%94%B7%E5%AD%90%E5%87%8C%E6%99%A8%E6%93%85%E8%87%AA%E8%BF%9B%E5%90%88%E7%A7%9F%E5%A5%B3%E5%AD%90%E6%88%BF%E9%97%B4%E8%A2%AB%E6%8B%98%22%7D&rank=16&style_id=40132&topic_id=7134984122031669279","hot":"2118103","icon":"","cover":"https://p6.toutiaoimg.com/img/top-static-files-outer/breaknews/d57367f9-7780-41b6-9f28-96dc6fe01819~cs_noop.png"},{"title":"联合国呼吁对杜金娜案进行全面调查","url":"https://www.toutiao.com/amos_land_page/?category_name=topic_innerflow&event_type=hot_board&log_pb=%7B%22category_name%22%3A%22topic_innerflow%22%2C%22cluster_type%22%3A%226%22%2C%22enter_from%22%3A%22click_category%22%2C%22entrance_hotspot%22%3A%22outside%22%2C%22event_type%22%3A%22hot_board%22%2C%22hot_board_cluster_id%22%3A%227134884718536818727%22%2C%22hot_board_impr_id%22%3A%2220220824054117010135119019165D8022%22%2C%22jump_page%22%3A%22hot_board_page%22%2C%22location%22%3A%22news_hot_card%22%2C%22page_location%22%3A%22hot_board_page%22%2C%22rank%22%3A%2217%22%2C%22source%22%3A%22trending_tab%22%2C%22style_id%22%3A%2240132%22%2C%22title%22%3A%22%E8%81%94%E5%90%88%E5%9B%BD%E5%91%BC%E5%90%81%E5%AF%B9%E6%9D%9C%E9%87%91%E5%A8%9C%E6%A1%88%E8%BF%9B%E8%A1%8C%E5%85%A8%E9%9D%A2%E8%B0%83%E6%9F%A5%22%7D&rank=17&style_id=40132&topic_id=7134884718536818727","hot":"1916538","icon":"","cover":"https://p6.toutiaoimg.com/img/tos-cn-i-qvj2lq49k0/0882bfba7f5347e5aad340c0685da5de~cs_noop.png"},{"title":"广西警方悬赏：看到这4男1女请报警","url":"https://www.toutiao.com/amos_land_page/?category_name=topic_innerflow&event_type=hot_board&log_pb=%7B%22category_name%22%3A%22topic_innerflow%22%2C%22cluster_type%22%3A%226%22%2C%22enter_from%22%3A%22click_category%22%2C%22entrance_hotspot%22%3A%22outside%22%2C%22event_type%22%3A%22hot_board%22%2C%22hot_board_cluster_id%22%3A%227134927676866822147%22%2C%22hot_board_impr_id%22%3A%2220220824054117010135119019165D8022%22%2C%22jump_page%22%3A%22hot_board_page%22%2C%22location%22%3A%22news_hot_card%22%2C%22page_location%22%3A%22hot_board_page%22%2C%22rank%22%3A%2218%22%2C%22source%22%3A%22trending_tab%22%2C%22style_id%22%3A%2240132%22%2C%22title%22%3A%22%E5%B9%BF%E8%A5%BF%E8%AD%A6%E6%96%B9%E6%82%AC%E8%B5%8F%EF%BC%9A%E7%9C%8B%E5%88%B0%E8%BF%994%E7%94%B71%E5%A5%B3%E8%AF%B7%E6%8A%A5%E8%AD%A6%22%7D&rank=18&style_id=40132&topic_id=7134927676866822147","hot":"1734156","icon":"","cover":"https://p26.toutiaoimg.com/img/top-static-files-outer/breaknews/57851e79-33c3-4b4e-a3e7-83ef6d7ad083~cs_noop.png"},{"title":"市委书记敛财16年 落马后多干部被查","url":"https://www.toutiao.com/amos_land_page/?category_name=topic_innerflow&event_type=hot_board&log_pb=%7B%22category_name%22%3A%22topic_innerflow%22%2C%22cluster_type%22%3A%222%22%2C%22enter_from%22%3A%22click_category%22%2C%22entrance_hotspot%22%3A%22outside%22%2C%22event_type%22%3A%22hot_board%22%2C%22hot_board_cluster_id%22%3A%227134977507236773923%22%2C%22hot_board_impr_id%22%3A%2220220824054117010135119019165D8022%22%2C%22jump_page%22%3A%22hot_board_page%22%2C%22location%22%3A%22news_hot_card%22%2C%22page_location%22%3A%22hot_board_page%22%2C%22rank%22%3A%2219%22%2C%22source%22%3A%22trending_tab%22%2C%22style_id%22%3A%2240132%22%2C%22title%22%3A%22%E5%B8%82%E5%A7%94%E4%B9%A6%E8%AE%B0%E6%95%9B%E8%B4%A216%E5%B9%B4+%E8%90%BD%E9%A9%AC%E5%90%8E%E5%A4%9A%E5%B9%B2%E9%83%A8%E8%A2%AB%E6%9F%A5%22%7D&rank=19&style_id=40132&topic_id=7134977507236773923","hot":"1569129","icon":"","cover":"https://p26.toutiaoimg.com/img/tos-cn-i-qvj2lq49k0/f2195c58b8734d6ca70befd02a5c886a~cs_noop.png"},{"title":"李立群说一个中国的立场永远不变","url":"https://www.toutiao.com/amos_land_page/?category_name=topic_innerflow&event_type=hot_board&log_pb=%7B%22category_name%22%3A%22topic_innerflow%22%2C%22cluster_type%22%3A%221%22%2C%22enter_from%22%3A%22click_category%22%2C%22entrance_hotspot%22%3A%22outside%22%2C%22event_type%22%3A%22hot_board%22%2C%22hot_board_cluster_id%22%3A%227134305004802080809%22%2C%22hot_board_impr_id%22%3A%2220220824054117010135119019165D8022%22%2C%22jump_page%22%3A%22hot_board_page%22%2C%22location%22%3A%22news_hot_card%22%2C%22page_location%22%3A%22hot_board_page%22%2C%22rank%22%3A%2220%22%2C%22source%22%3A%22trending_tab%22%2C%22style_id%22%3A%2240132%22%2C%22title%22%3A%22%E6%9D%8E%E7%AB%8B%E7%BE%A4%E8%AF%B4%E4%B8%80%E4%B8%AA%E4%B8%AD%E5%9B%BD%E7%9A%84%E7%AB%8B%E5%9C%BA%E6%B0%B8%E8%BF%9C%E4%B8%8D%E5%8F%98%22%7D&rank=20&style_id=40132&topic_id=7134305004802080809","hot":"1419807","icon":"","cover":"https://p6.toutiaoimg.com/img/top-static-files-outer/breaknews/d9c0e960-9a52-469e-988c-601c0079472a~cs_noop.png"},{"title":"出租车司机摸醉酒女乘客大腿被抓","url":"https://www.toutiao.com/amos_land_page/?category_name=topic_innerflow&event_type=hot_board&log_pb=%7B%22category_name%22%3A%22topic_innerflow%22%2C%22cluster_type%22%3A%228%22%2C%22enter_from%22%3A%22click_category%22%2C%22entrance_hotspot%22%3A%22outside%22%2C%22event_type%22%3A%22hot_board%22%2C%22hot_board_cluster_id%22%3A%227134880535163174948%22%2C%22hot_board_impr_id%22%3A%2220220824054117010135119019165D8022%22%2C%22jump_page%22%3A%22hot_board_page%22%2C%22location%22%3A%22news_hot_card%22%2C%22page_location%22%3A%22hot_board_page%22%2C%22rank%22%3A%2221%22%2C%22source%22%3A%22trending_tab%22%2C%22style_id%22%3A%2240132%22%2C%22title%22%3A%22%E5%87%BA%E7%A7%9F%E8%BD%A6%E5%8F%B8%E6%9C%BA%E6%91%B8%E9%86%89%E9%85%92%E5%A5%B3%E4%B9%98%E5%AE%A2%E5%A4%A7%E8%85%BF%E8%A2%AB%E6%8A%93%22%7D&rank=21&style_id=40132&topic_id=7134880535163174948","hot":"1284694","icon":"","cover":"https://p26.toutiaoimg.com/img/top-static-files-outer/breaknews/c0123cda-8a00-4eee-9a27-5cc06ba099cf~cs_noop.png"},{"title":"曾志伟回应确诊新冠","url":"https://www.toutiao.com/amos_land_page/?category_name=topic_innerflow&event_type=hot_board&log_pb=%7B%22category_name%22%3A%22topic_innerflow%22%2C%22cluster_type%22%3A%222%22%2C%22enter_from%22%3A%22click_category%22%2C%22entrance_hotspot%22%3A%22outside%22%2C%22event_type%22%3A%22hot_board%22%2C%22hot_board_cluster_id%22%3A%227134715972585259008%22%2C%22hot_board_impr_id%22%3A%2220220824054117010135119019165D8022%22%2C%22jump_page%22%3A%22hot_board_page%22%2C%22location%22%3A%22news_hot_card%22%2C%22page_location%22%3A%22hot_board_page%22%2C%22rank%22%3A%2222%22%2C%22source%22%3A%22trending_tab%22%2C%22style_id%22%3A%2240132%22%2C%22title%22%3A%22%E6%9B%BE%E5%BF%97%E4%BC%9F%E5%9B%9E%E5%BA%94%E7%A1%AE%E8%AF%8A%E6%96%B0%E5%86%A0%22%7D&rank=22&style_id=40132&topic_id=7134715972585259008","hot":"1162439","icon":"","cover":"https://p6.toutiaoimg.com/img/tos-cn-i-qvj2lq49k0/b6b2a904db6f48b583dbbf95bcbaf91a~cs_noop.png"},{"title":"台风“马鞍”或正面登陆广东","url":"https://www.toutiao.com/amos_land_page/?category_name=topic_innerflow&event_type=hot_board&log_pb=%7B%22category_name%22%3A%22topic_innerflow%22%2C%22cluster_type%22%3A%229%22%2C%22enter_from%22%3A%22click_category%22%2C%22entrance_hotspot%22%3A%22outside%22%2C%22event_type%22%3A%22hot_board%22%2C%22hot_board_cluster_id%22%3A%227134619638414983204%22%2C%22hot_board_impr_id%22%3A%2220220824054117010135119019165D8022%22%2C%22jump_page%22%3A%22hot_board_page%22%2C%22location%22%3A%22news_hot_card%22%2C%22page_location%22%3A%22hot_board_page%22%2C%22rank%22%3A%2223%22%2C%22source%22%3A%22trending_tab%22%2C%22style_id%22%3A%2240132%22%2C%22title%22%3A%22%E5%8F%B0%E9%A3%8E%E2%80%9C%E9%A9%AC%E9%9E%8D%E2%80%9D%E6%88%96%E6%AD%A3%E9%9D%A2%E7%99%BB%E9%99%86%E5%B9%BF%E4%B8%9C%22%7D&rank=23&style_id=40132&topic_id=7134619638414983204","hot":"1051818","icon":"","cover":"https://p26.toutiaoimg.com/img/tos-cn-i-qvj2lq49k0/7d8615f901b044c89010cdced3236a5c~cs_noop.png"},{"title":"媒体：刘翔峰拒绝回应网络流言","url":"https://www.toutiao.com/amos_land_page/?category_name=topic_innerflow&event_type=hot_board&log_pb=%7B%22category_name%22%3A%22topic_innerflow%22%2C%22cluster_type%22%3A%226%22%2C%22enter_from%22%3A%22click_category%22%2C%22entrance_hotspot%22%3A%22outside%22%2C%22event_type%22%3A%22hot_board%22%2C%22hot_board_cluster_id%22%3A%227135038003247841288%22%2C%22hot_board_impr_id%22%3A%2220220824054117010135119019165D8022%22%2C%22jump_page%22%3A%22hot_board_page%22%2C%22location%22%3A%22news_hot_card%22%2C%22page_location%22%3A%22hot_board_page%22%2C%22rank%22%3A%2224%22%2C%22source%22%3A%22trending_tab%22%2C%22style_id%22%3A%2240132%22%2C%22title%22%3A%22%E5%AA%92%E4%BD%93%EF%BC%9A%E5%88%98%E7%BF%94%E5%B3%B0%E6%8B%92%E7%BB%9D%E5%9B%9E%E5%BA%94%E7%BD%91%E7%BB%9C%E6%B5%81%E8%A8%80%22%7D&rank=24&style_id=40132&topic_id=7135038003247841288","hot":"951725","icon":"","cover":"https://p6.toutiaoimg.com/img/tos-cn-i-qvj2lq49k0/3f043483909e407087135817f1d40584~cs_noop.png"},{"title":"三峡移民30年 老汉带桃树永别故乡","url":"https://www.toutiao.com/amos_land_page/?category_name=topic_innerflow&event_type=hot_board&log_pb=%7B%22category_name%22%3A%22topic_innerflow%22%2C%22cluster_type%22%3A%221%22%2C%22enter_from%22%3A%22click_category%22%2C%22entrance_hotspot%22%3A%22outside%22%2C%22event_type%22%3A%22hot_board%22%2C%22hot_board_cluster_id%22%3A%227134895934294458376%22%2C%22hot_board_impr_id%22%3A%2220220824054117010135119019165D8022%22%2C%22jump_page%22%3A%22hot_board_page%22%2C%22location%22%3A%22news_hot_card%22%2C%22page_location%22%3A%22hot_board_page%22%2C%22rank%22%3A%2225%22%2C%22source%22%3A%22trending_tab%22%2C%22style_id%22%3A%2240132%22%2C%22title%22%3A%22%E4%B8%89%E5%B3%A1%E7%A7%BB%E6%B0%9130%E5%B9%B4+%E8%80%81%E6%B1%89%E5%B8%A6%E6%A1%83%E6%A0%91%E6%B0%B8%E5%88%AB%E6%95%85%E4%B9%A1%22%7D&rank=25&style_id=40132&topic_id=7134895934294458376","hot":"861156","icon":"","cover":"https://p6.toutiaoimg.com/img/tos-cn-i-qvj2lq49k0/d85e173d6113448894010e246e60c203~cs_noop.png"},{"title":"四川人大常委会原副主任王铭晖被捕","url":"https://www.toutiao.com/amos_land_page/?category_name=topic_innerflow&event_type=hot_board&log_pb=%7B%22category_name%22%3A%22topic_innerflow%22%2C%22cluster_type%22%3A%228%22%2C%22enter_from%22%3A%22click_category%22%2C%22entrance_hotspot%22%3A%22outside%22%2C%22event_type%22%3A%22hot_board%22%2C%22hot_board_cluster_id%22%3A%227134501552449929246%22%2C%22hot_board_impr_id%22%3A%2220220824054117010135119019165D8022%22%2C%22jump_page%22%3A%22hot_board_page%22%2C%22location%22%3A%22news_hot_card%22%2C%22page_location%22%3A%22hot_board_page%22%2C%22rank%22%3A%2226%22%2C%22source%22%3A%22trending_tab%22%2C%22style_id%22%3A%2240132%22%2C%22title%22%3A%22%E5%9B%9B%E5%B7%9D%E4%BA%BA%E5%A4%A7%E5%B8%B8%E5%A7%94%E4%BC%9A%E5%8E%9F%E5%89%AF%E4%B8%BB%E4%BB%BB%E7%8E%8B%E9%93%AD%E6%99%96%E8%A2%AB%E6%8D%95%22%7D&rank=26&style_id=40132&topic_id=7134501552449929246","hot":"779206","icon":"","cover":"https://p3.toutiaoimg.com/img/top-static-files-outer/breaknews/312b09ce-9c3e-4888-b47d-d79e6f22c2f5~cs_noop.png"},{"title":"油价五连降 0号柴油重回7元时代","url":"https://www.toutiao.com/amos_land_page/?category_name=topic_innerflow&event_type=hot_board&log_pb=%7B%22category_name%22%3A%22topic_innerflow%22%2C%22cluster_type%22%3A%222%22%2C%22enter_from%22%3A%22click_category%22%2C%22entrance_hotspot%22%3A%22outside%22%2C%22event_type%22%3A%22hot_board%22%2C%22hot_board_cluster_id%22%3A%227134336338077155365%22%2C%22hot_board_impr_id%22%3A%2220220824054117010135119019165D8022%22%2C%22jump_page%22%3A%22hot_board_page%22%2C%22location%22%3A%22news_hot_card%22%2C%22page_location%22%3A%22hot_board_page%22%2C%22rank%22%3A%2227%22%2C%22source%22%3A%22trending_tab%22%2C%22style_id%22%3A%2240132%22%2C%22title%22%3A%22%E6%B2%B9%E4%BB%B7%E4%BA%94%E8%BF%9E%E9%99%8D+0%E5%8F%B7%E6%9F%B4%E6%B2%B9%E9%87%8D%E5%9B%9E7%E5%85%83%E6%97%B6%E4%BB%A3%22%7D&rank=27&style_id=40132&topic_id=7134336338077155365","hot":"705055","icon":"","cover":"https://p6.toutiaoimg.com/img/top-static-files-outer/breaknews/64a42392-64d8-4cda-a715-abf1bc7f5a08~cs_noop.png"},{"title":"两架俄轰炸机在日本海上空完成巡逻","url":"https://www.toutiao.com/amos_land_page/?category_name=topic_innerflow&event_type=hot_board&log_pb=%7B%22category_name%22%3A%22topic_innerflow%22%2C%22cluster_type%22%3A%226%22%2C%22enter_from%22%3A%22click_category%22%2C%22entrance_hotspot%22%3A%22outside%22%2C%22event_type%22%3A%22hot_board%22%2C%22hot_board_cluster_id%22%3A%227134975330724347912%22%2C%22hot_board_impr_id%22%3A%2220220824054117010135119019165D8022%22%2C%22jump_page%22%3A%22hot_board_page%22%2C%22location%22%3A%22news_hot_card%22%2C%22page_location%22%3A%22hot_board_page%22%2C%22rank%22%3A%2228%22%2C%22source%22%3A%22trending_tab%22%2C%22style_id%22%3A%2240132%22%2C%22title%22%3A%22%E4%B8%A4%E6%9E%B6%E4%BF%84%E8%BD%B0%E7%82%B8%E6%9C%BA%E5%9C%A8%E6%97%A5%E6%9C%AC%E6%B5%B7%E4%B8%8A%E7%A9%BA%E5%AE%8C%E6%88%90%E5%B7%A1%E9%80%BB%22%7D&rank=28&style_id=40132&topic_id=7134975330724347912","hot":"637960","icon":"","cover":"https://p26.toutiaoimg.com/img/top-static-files-outer/breaknews/c8a14d94-1bb8-45b3-9746-3ef501c9cec3~cs_noop.png"},{"title":"5旬大妈狂摇半小时摇折景区桥围栏","url":"https://www.toutiao.com/amos_land_page/?category_name=topic_innerflow&event_type=hot_board&log_pb=%7B%22category_name%22%3A%22topic_innerflow%22%2C%22cluster_type%22%3A%222%22%2C%22enter_from%22%3A%22click_category%22%2C%22entrance_hotspot%22%3A%22outside%22%2C%22event_type%22%3A%22hot_board%22%2C%22hot_board_cluster_id%22%3A%227134307019338547207%22%2C%22hot_board_impr_id%22%3A%2220220824054117010135119019165D8022%22%2C%22jump_page%22%3A%22hot_board_page%22%2C%22location%22%3A%22news_hot_card%22%2C%22page_location%22%3A%22hot_board_page%22%2C%22rank%22%3A%2229%22%2C%22source%22%3A%22trending_tab%22%2C%22style_id%22%3A%2240132%22%2C%22title%22%3A%225%E6%97%AC%E5%A4%A7%E5%A6%88%E7%8B%82%E6%91%87%E5%8D%8A%E5%B0%8F%E6%97%B6%E6%91%87%E6%8A%98%E6%99%AF%E5%8C%BA%E6%A1%A5%E5%9B%B4%E6%A0%8F%22%7D&rank=29&style_id=40132&topic_id=7134307019338547207","hot":"577250","icon":"","cover":"https://p3.toutiaoimg.com/img/top-static-files-outer/breaknews/ac7bc709-1b8c-40da-af50-f00cb489f1da~cs_noop.png"},{"title":"女子获刑车辆被扣 车内20万首饰丢失","url":"https://www.toutiao.com/amos_land_page/?category_name=topic_innerflow&event_type=hot_board&log_pb=%7B%22category_name%22%3A%22topic_innerflow%22%2C%22cluster_type%22%3A%221%22%2C%22enter_from%22%3A%22click_category%22%2C%22entrance_hotspot%22%3A%22outside%22%2C%22event_type%22%3A%22hot_board%22%2C%22hot_board_cluster_id%22%3A%227135010327124508708%22%2C%22hot_board_impr_id%22%3A%2220220824054117010135119019165D8022%22%2C%22jump_page%22%3A%22hot_board_page%22%2C%22location%22%3A%22news_hot_card%22%2C%22page_location%22%3A%22hot_board_page%22%2C%22rank%22%3A%2230%22%2C%22source%22%3A%22trending_tab%22%2C%22style_id%22%3A%2240132%22%2C%22title%22%3A%22%E5%A5%B3%E5%AD%90%E8%8E%B7%E5%88%91%E8%BD%A6%E8%BE%86%E8%A2%AB%E6%89%A3+%E8%BD%A6%E5%86%8520%E4%B8%87%E9%A6%96%E9%A5%B0%E4%B8%A2%E5%A4%B1%22%7D&rank=30&style_id=40132&topic_id=7135010327124508708","hot":"522317","icon":"","cover":"https://p3.toutiaoimg.com/img/tos-cn-i-qvj2lq49k0/ab1a49cab14145cda4a378b4121f8978~cs_noop.png"},{"title":"男子两年盗窃近千件女性内衣裤落网","url":"https://www.toutiao.com/amos_land_page/?category_name=topic_innerflow&event_type=hot_board&log_pb=%7B%22category_name%22%3A%22topic_innerflow%22%2C%22cluster_type%22%3A%220%22%2C%22enter_from%22%3A%22click_category%22%2C%22entrance_hotspot%22%3A%22outside%22%2C%22event_type%22%3A%22hot_board%22%2C%22hot_board_cluster_id%22%3A%227134893121191542788%22%2C%22hot_board_impr_id%22%3A%2220220824054117010135119019165D8022%22%2C%22jump_page%22%3A%22hot_board_page%22%2C%22location%22%3A%22news_hot_card%22%2C%22page_location%22%3A%22hot_board_page%22%2C%22rank%22%3A%2231%22%2C%22source%22%3A%22trending_tab%22%2C%22style_id%22%3A%2240132%22%2C%22title%22%3A%22%E7%94%B7%E5%AD%90%E4%B8%A4%E5%B9%B4%E7%9B%97%E7%AA%83%E8%BF%91%E5%8D%83%E4%BB%B6%E5%A5%B3%E6%80%A7%E5%86%85%E8%A1%A3%E8%A3%A4%E8%90%BD%E7%BD%91%22%7D&rank=31&style_id=40132&topic_id=7134893121191542788","hot":"472612","icon":"","cover":"https://p9.toutiaoimg.com/img/tos-cn-i-qvj2lq49k0/44f8d1939a134f94ab1b5436d8acfc3b~cs_noop.png"},{"title":"原券商研究助理杀进世界小姐总决赛","url":"https://www.toutiao.com/amos_land_page/?category_name=topic_innerflow&event_type=hot_board&log_pb=%7B%22category_name%22%3A%22topic_innerflow%22%2C%22cluster_type%22%3A%220%22%2C%22enter_from%22%3A%22click_category%22%2C%22entrance_hotspot%22%3A%22outside%22%2C%22event_type%22%3A%22hot_board%22%2C%22hot_board_cluster_id%22%3A%227134735334222331935%22%2C%22hot_board_impr_id%22%3A%2220220824054117010135119019165D8022%22%2C%22jump_page%22%3A%22hot_board_page%22%2C%22location%22%3A%22news_hot_card%22%2C%22page_location%22%3A%22hot_board_page%22%2C%22rank%22%3A%2232%22%2C%22source%22%3A%22trending_tab%22%2C%22style_id%22%3A%2240132%22%2C%22title%22%3A%22%E5%8E%9F%E5%88%B8%E5%95%86%E7%A0%94%E7%A9%B6%E5%8A%A9%E7%90%86%E6%9D%80%E8%BF%9B%E4%B8%96%E7%95%8C%E5%B0%8F%E5%A7%90%E6%80%BB%E5%86%B3%E8%B5%9B%22%7D&rank=32&style_id=40132&topic_id=7134735334222331935","hot":"427637","icon":"","cover":"https://p26.toutiaoimg.com/img/top-static-files-outer/breaknews/4a51ea70-a72d-455c-8b6e-afb03e948a2a~cs_noop.png"},{"title":"贾平凹之女拟入中国作协 官方回应","url":"https://www.toutiao.com/amos_land_page/?category_name=topic_innerflow&event_type=hot_board&log_pb=%7B%22category_name%22%3A%22topic_innerflow%22%2C%22cluster_type%22%3A%225%22%2C%22enter_from%22%3A%22click_category%22%2C%22entrance_hotspot%22%3A%22outside%22%2C%22event_type%22%3A%22hot_board%22%2C%22hot_board_cluster_id%22%3A%227135026583890300429%22%2C%22hot_board_impr_id%22%3A%2220220824054117010135119019165D8022%22%2C%22jump_page%22%3A%22hot_board_page%22%2C%22location%22%3A%22news_hot_card%22%2C%22page_location%22%3A%22hot_board_page%22%2C%22rank%22%3A%2233%22%2C%22source%22%3A%22trending_tab%22%2C%22style_id%22%3A%2240132%22%2C%22title%22%3A%22%E8%B4%BE%E5%B9%B3%E5%87%B9%E4%B9%8B%E5%A5%B3%E6%8B%9F%E5%85%A5%E4%B8%AD%E5%9B%BD%E4%BD%9C%E5%8D%8F+%E5%AE%98%E6%96%B9%E5%9B%9E%E5%BA%94%22%7D&rank=33&style_id=40132&topic_id=7135026583890300429","hot":"386942","icon":"","cover":"https://p3.toutiaoimg.com/img/tos-cn-i-qvj2lq49k0/c238f75c641f4b95b1a02f4ef7d3a44f~cs_noop.png"},{"title":"“中国最后女酋长”去世 享年101岁","url":"https://www.toutiao.com/amos_land_page/?category_name=topic_innerflow&event_type=hot_board&log_pb=%7B%22category_name%22%3A%22topic_innerflow%22%2C%22cluster_type%22%3A%221%22%2C%22enter_from%22%3A%22click_category%22%2C%22entrance_hotspot%22%3A%22outside%22%2C%22event_type%22%3A%22hot_board%22%2C%22hot_board_cluster_id%22%3A%227134648488482045983%22%2C%22hot_board_impr_id%22%3A%2220220824054117010135119019165D8022%22%2C%22jump_page%22%3A%22hot_board_page%22%2C%22location%22%3A%22news_hot_card%22%2C%22page_location%22%3A%22hot_board_page%22%2C%22rank%22%3A%2234%22%2C%22source%22%3A%22trending_tab%22%2C%22style_id%22%3A%2240132%22%2C%22title%22%3A%22%E2%80%9C%E4%B8%AD%E5%9B%BD%E6%9C%80%E5%90%8E%E5%A5%B3%E9%85%8B%E9%95%BF%E2%80%9D%E5%8E%BB%E4%B8%96+%E4%BA%AB%E5%B9%B4101%E5%B2%81%22%7D&rank=34&style_id=40132&topic_id=7134648488482045983","hot":"350120","icon":"","cover":"https://p3.toutiaoimg.com/img/tos-cn-i-qvj2lq49k0/924d855bd5cd4f1781b15d13a4fe4979~cs_noop.png"},{"title":"老人在自家撒药致邻居羊死亡被诉","url":"https://www.toutiao.com/amos_land_page/?category_name=topic_innerflow&event_type=hot_board&log_pb=%7B%22category_name%22%3A%22topic_innerflow%22%2C%22cluster_type%22%3A%222%22%2C%22enter_from%22%3A%22click_category%22%2C%22entrance_hotspot%22%3A%22outside%22%2C%22event_type%22%3A%22hot_board%22%2C%22hot_board_cluster_id%22%3A%227135014618057375757%22%2C%22hot_board_impr_id%22%3A%2220220824054117010135119019165D8022%22%2C%22jump_page%22%3A%22hot_board_page%22%2C%22location%22%3A%22news_hot_card%22%2C%22page_location%22%3A%22hot_board_page%22%2C%22rank%22%3A%2235%22%2C%22source%22%3A%22trending_tab%22%2C%22style_id%22%3A%2240132%22%2C%22title%22%3A%22%E8%80%81%E4%BA%BA%E5%9C%A8%E8%87%AA%E5%AE%B6%E6%92%92%E8%8D%AF%E8%87%B4%E9%82%BB%E5%B1%85%E7%BE%8A%E6%AD%BB%E4%BA%A1%E8%A2%AB%E8%AF%89%22%7D&rank=35&style_id=40132&topic_id=7135014618057375757","hot":"316801","icon":"","cover":"https://p26.toutiaoimg.com/img/tos-cn-i-qvj2lq49k0/036ba566c7844985b137723c5498a8a7~cs_noop.png"},{"title":"极度濒危植物尖齿卫矛隐世百年再现","url":"https://www.toutiao.com/amos_land_page/?category_name=topic_innerflow&event_type=hot_board&log_pb=%7B%22category_name%22%3A%22topic_innerflow%22%2C%22cluster_type%22%3A%228%22%2C%22enter_from%22%3A%22click_category%22%2C%22entrance_hotspot%22%3A%22outside%22%2C%22event_type%22%3A%22hot_board%22%2C%22hot_board_cluster_id%22%3A%227134669943794057252%22%2C%22hot_board_impr_id%22%3A%2220220824054117010135119019165D8022%22%2C%22jump_page%22%3A%22hot_board_page%22%2C%22location%22%3A%22news_hot_card%22%2C%22page_location%22%3A%22hot_board_page%22%2C%22rank%22%3A%2236%22%2C%22source%22%3A%22trending_tab%22%2C%22style_id%22%3A%2240132%22%2C%22title%22%3A%22%E6%9E%81%E5%BA%A6%E6%BF%92%E5%8D%B1%E6%A4%8D%E7%89%A9%E5%B0%96%E9%BD%BF%E5%8D%AB%E7%9F%9B%E9%9A%90%E4%B8%96%E7%99%BE%E5%B9%B4%E5%86%8D%E7%8E%B0%22%7D&rank=36&style_id=40132&topic_id=7134669943794057252","hot":"286654","icon":"","cover":"https://p9.toutiaoimg.com/img/top-static-files-outer/breaknews/9d7121a5-4a2b-4ecb-9885-2c950a406584~cs_noop.png"},{"title":"女孩江苏买房每天坐高铁去上海上班","url":"https://www.toutiao.com/amos_land_page/?category_name=topic_innerflow&event_type=hot_board&log_pb=%7B%22category_name%22%3A%22topic_innerflow%22%2C%22cluster_type%22%3A%228%22%2C%22enter_from%22%3A%22click_category%22%2C%22entrance_hotspot%22%3A%22outside%22%2C%22event_type%22%3A%22hot_board%22%2C%22hot_board_cluster_id%22%3A%227134712740622385182%22%2C%22hot_board_impr_id%22%3A%2220220824054117010135119019165D8022%22%2C%22jump_page%22%3A%22hot_board_page%22%2C%22location%22%3A%22news_hot_card%22%2C%22page_location%22%3A%22hot_board_page%22%2C%22rank%22%3A%2237%22%2C%22source%22%3A%22trending_tab%22%2C%22style_id%22%3A%2240132%22%2C%22title%22%3A%22%E5%A5%B3%E5%AD%A9%E6%B1%9F%E8%8B%8F%E4%B9%B0%E6%88%BF%E6%AF%8F%E5%A4%A9%E5%9D%90%E9%AB%98%E9%93%81%E5%8E%BB%E4%B8%8A%E6%B5%B7%E4%B8%8A%E7%8F%AD%22%7D&rank=37&style_id=40132&topic_id=7134712740622385182","hot":"259375","icon":"","cover":"https://p6.toutiaoimg.com/img/top-static-files-outer/breaknews/4f3da88f-d4af-47df-a9d2-b7b8f860afc2~cs_noop.png"},{"title":"100多分贝巨响24小时猛袭 居民头痛","url":"https://www.toutiao.com/amos_land_page/?category_name=topic_innerflow&event_type=hot_board&log_pb=%7B%22category_name%22%3A%22topic_innerflow%22%2C%22cluster_type%22%3A%222%22%2C%22enter_from%22%3A%22click_category%22%2C%22entrance_hotspot%22%3A%22outside%22%2C%22event_type%22%3A%22hot_board%22%2C%22hot_board_cluster_id%22%3A%227134979289748865059%22%2C%22hot_board_impr_id%22%3A%2220220824054117010135119019165D8022%22%2C%22jump_page%22%3A%22hot_board_page%22%2C%22location%22%3A%22news_hot_card%22%2C%22page_location%22%3A%22hot_board_page%22%2C%22rank%22%3A%2238%22%2C%22source%22%3A%22trending_tab%22%2C%22style_id%22%3A%2240132%22%2C%22title%22%3A%22100%E5%A4%9A%E5%88%86%E8%B4%9D%E5%B7%A8%E5%93%8D24%E5%B0%8F%E6%97%B6%E7%8C%9B%E8%A2%AD+%E5%B1%85%E6%B0%91%E5%A4%B4%E7%97%9B%22%7D&rank=38&style_id=40132&topic_id=7134979289748865059","hot":"234692","icon":"","cover":"https://p26.toutiaoimg.com/img/top-static-files-outer/breaknews/7ac3de26-58b4-4698-b410-16625afcaacb~cs_noop.png"},{"title":"为打破“被清算”魔咒 文在寅有多拼","url":"https://www.toutiao.com/amos_land_page/?category_name=topic_innerflow&event_type=hot_board&log_pb=%7B%22category_name%22%3A%22topic_innerflow%22%2C%22cluster_type%22%3A%221%22%2C%22enter_from%22%3A%22click_category%22%2C%22entrance_hotspot%22%3A%22outside%22%2C%22event_type%22%3A%22hot_board%22%2C%22hot_board_cluster_id%22%3A%227134888819874070541%22%2C%22hot_board_impr_id%22%3A%2220220824054117010135119019165D8022%22%2C%22jump_page%22%3A%22hot_board_page%22%2C%22location%22%3A%22news_hot_card%22%2C%22page_location%22%3A%22hot_board_page%22%2C%22rank%22%3A%2239%22%2C%22source%22%3A%22trending_tab%22%2C%22style_id%22%3A%2240132%22%2C%22title%22%3A%22%E4%B8%BA%E6%89%93%E7%A0%B4%E2%80%9C%E8%A2%AB%E6%B8%85%E7%AE%97%E2%80%9D%E9%AD%94%E5%92%92+%E6%96%87%E5%9C%A8%E5%AF%85%E6%9C%89%E5%A4%9A%E6%8B%BC%22%7D&rank=39&style_id=40132&topic_id=7134888819874070541","hot":"212358","icon":"","cover":"https://p6.toutiaoimg.com/img/tos-cn-i-qvj2lq49k0/bd04175df28e4ea69662cad596aa272f~cs_noop.png"},{"title":"16位外甥暑假到舅舅家：住55天花6万","url":"https://www.toutiao.com/amos_land_page/?category_name=topic_innerflow&event_type=hot_board&log_pb=%7B%22category_name%22%3A%22topic_innerflow%22%2C%22cluster_type%22%3A%220%22%2C%22enter_from%22%3A%22click_category%22%2C%22entrance_hotspot%22%3A%22outside%22%2C%22event_type%22%3A%22hot_board%22%2C%22hot_board_cluster_id%22%3A%227134836871741308965%22%2C%22hot_board_impr_id%22%3A%2220220824054117010135119019165D8022%22%2C%22jump_page%22%3A%22hot_board_page%22%2C%22location%22%3A%22news_hot_card%22%2C%22page_location%22%3A%22hot_board_page%22%2C%22rank%22%3A%2240%22%2C%22source%22%3A%22trending_tab%22%2C%22style_id%22%3A%2240132%22%2C%22title%22%3A%2216%E4%BD%8D%E5%A4%96%E7%94%A5%E6%9A%91%E5%81%87%E5%88%B0%E8%88%85%E8%88%85%E5%AE%B6%EF%BC%9A%E4%BD%8F55%E5%A4%A9%E8%8A%B16%E4%B8%87%22%7D&rank=40&style_id=40132&topic_id=7134836871741308965","hot":"192149","icon":"","cover":"https://p26.toutiaoimg.com/img/top-static-files-outer/breaknews/887c811f-1796-465d-ae5e-14e96ed051c4~cs_noop.png"},{"title":"院方称林志颖已返家休养","url":"https://www.toutiao.com/amos_land_page/?category_name=topic_innerflow&event_type=hot_board&log_pb=%7B%22category_name%22%3A%22topic_innerflow%22%2C%22cluster_type%22%3A%222%22%2C%22enter_from%22%3A%22click_category%22%2C%22entrance_hotspot%22%3A%22outside%22%2C%22event_type%22%3A%22hot_board%22%2C%22hot_board_cluster_id%22%3A%227134652765699047462%22%2C%22hot_board_impr_id%22%3A%2220220824054117010135119019165D8022%22%2C%22jump_page%22%3A%22hot_board_page%22%2C%22location%22%3A%22news_hot_card%22%2C%22page_location%22%3A%22hot_board_page%22%2C%22rank%22%3A%2241%22%2C%22source%22%3A%22trending_tab%22%2C%22style_id%22%3A%2240132%22%2C%22title%22%3A%22%E9%99%A2%E6%96%B9%E7%A7%B0%E6%9E%97%E5%BF%97%E9%A2%96%E5%B7%B2%E8%BF%94%E5%AE%B6%E4%BC%91%E5%85%BB%22%7D&rank=41&style_id=40132&topic_id=7134652765699047462","hot":"173864","icon":"","cover":"https://p6.toutiaoimg.com/img/top-static-files-outer/breaknews/ed0189bb-c58a-4910-a45e-4fcf01cf38d7~cs_noop.png"},{"title":"今年是未来10年最凉爽1年？官方辟谣","url":"https://www.toutiao.com/amos_land_page/?category_name=topic_innerflow&event_type=hot_board&log_pb=%7B%22category_name%22%3A%22topic_innerflow%22%2C%22cluster_type%22%3A%220%22%2C%22enter_from%22%3A%22click_category%22%2C%22entrance_hotspot%22%3A%22outside%22%2C%22event_type%22%3A%22hot_board%22%2C%22hot_board_cluster_id%22%3A%227134568263064748064%22%2C%22hot_board_impr_id%22%3A%2220220824054117010135119019165D8022%22%2C%22jump_page%22%3A%22hot_board_page%22%2C%22location%22%3A%22news_hot_card%22%2C%22page_location%22%3A%22hot_board_page%22%2C%22rank%22%3A%2242%22%2C%22source%22%3A%22trending_tab%22%2C%22style_id%22%3A%2240132%22%2C%22title%22%3A%22%E4%BB%8A%E5%B9%B4%E6%98%AF%E6%9C%AA%E6%9D%A510%E5%B9%B4%E6%9C%80%E5%87%89%E7%88%BD1%E5%B9%B4%EF%BC%9F%E5%AE%98%E6%96%B9%E8%BE%9F%E8%B0%A3%22%7D&rank=42&style_id=40132&topic_id=7134568263064748064","hot":"157319","icon":"","cover":"https://p3.toutiaoimg.com/img/top-static-files-outer/breaknews/cc95fe26-5782-4e58-b910-8c74585c631d~cs_noop.png"},{"title":"华润置地原党委书记唐勇被查","url":"https://www.toutiao.com/amos_land_page/?category_name=topic_innerflow&event_type=hot_board&log_pb=%7B%22category_name%22%3A%22topic_innerflow%22%2C%22cluster_type%22%3A%225%22%2C%22enter_from%22%3A%22click_category%22%2C%22entrance_hotspot%22%3A%22outside%22%2C%22event_type%22%3A%22hot_board%22%2C%22hot_board_cluster_id%22%3A%227134960750816136718%22%2C%22hot_board_impr_id%22%3A%2220220824054117010135119019165D8022%22%2C%22jump_page%22%3A%22hot_board_page%22%2C%22location%22%3A%22news_hot_card%22%2C%22page_location%22%3A%22hot_board_page%22%2C%22rank%22%3A%2243%22%2C%22source%22%3A%22trending_tab%22%2C%22style_id%22%3A%2240132%22%2C%22title%22%3A%22%E5%8D%8E%E6%B6%A6%E7%BD%AE%E5%9C%B0%E5%8E%9F%E5%85%9A%E5%A7%94%E4%B9%A6%E8%AE%B0%E5%94%90%E5%8B%87%E8%A2%AB%E6%9F%A5%22%7D&rank=43&style_id=40132&topic_id=7134960750816136718","hot":"142348","icon":"","cover":"https://p26.toutiaoimg.com/img/top-static-files-outer/breaknews/e1f07a1a-4cb2-46e5-815a-cc0fca403b04~cs_noop.png"},{"title":"媒体：县城独居老人养老怎么办","url":"https://www.toutiao.com/amos_land_page/?category_name=topic_innerflow&event_type=hot_board&log_pb=%7B%22category_name%22%3A%22topic_innerflow%22%2C%22cluster_type%22%3A%221%22%2C%22enter_from%22%3A%22click_category%22%2C%22entrance_hotspot%22%3A%22outside%22%2C%22event_type%22%3A%22hot_board%22%2C%22hot_board_cluster_id%22%3A%227134917734747340830%22%2C%22hot_board_impr_id%22%3A%2220220824054117010135119019165D8022%22%2C%22jump_page%22%3A%22hot_board_page%22%2C%22location%22%3A%22news_hot_card%22%2C%22page_location%22%3A%22hot_board_page%22%2C%22rank%22%3A%2244%22%2C%22source%22%3A%22trending_tab%22%2C%22style_id%22%3A%2240132%22%2C%22title%22%3A%22%E5%AA%92%E4%BD%93%EF%BC%9A%E5%8E%BF%E5%9F%8E%E7%8B%AC%E5%B1%85%E8%80%81%E4%BA%BA%E5%85%BB%E8%80%81%E6%80%8E%E4%B9%88%E5%8A%9E%22%7D&rank=44&style_id=40132&topic_id=7134917734747340830","hot":"128801","icon":"","cover":"https://p26.toutiaoimg.com/img/tos-cn-i-qvj2lq49k0/159970e754e746b8963a272b6bdeb3dc~cs_noop.png"},{"title":"著名歌唱家多明戈疑涉人口贩卖案","url":"https://www.toutiao.com/amos_land_page/?category_name=topic_innerflow&event_type=hot_board&log_pb=%7B%22category_name%22%3A%22topic_innerflow%22%2C%22cluster_type%22%3A%222%22%2C%22enter_from%22%3A%22click_category%22%2C%22entrance_hotspot%22%3A%22outside%22%2C%22event_type%22%3A%22hot_board%22%2C%22hot_board_cluster_id%22%3A%227134523453134077993%22%2C%22hot_board_impr_id%22%3A%2220220824054117010135119019165D8022%22%2C%22jump_page%22%3A%22hot_board_page%22%2C%22location%22%3A%22news_hot_card%22%2C%22page_location%22%3A%22hot_board_page%22%2C%22rank%22%3A%2245%22%2C%22source%22%3A%22trending_tab%22%2C%22style_id%22%3A%2240132%22%2C%22title%22%3A%22%E8%91%97%E5%90%8D%E6%AD%8C%E5%94%B1%E5%AE%B6%E5%A4%9A%E6%98%8E%E6%88%88%E7%96%91%E6%B6%89%E4%BA%BA%E5%8F%A3%E8%B4%A9%E5%8D%96%E6%A1%88%22%7D&rank=45&style_id=40132&topic_id=7134523453134077993","hot":"116544","icon":"","cover":"https://p26.toutiaoimg.com/img/tos-cn-i-qvj2lq49k0/33c556b02abe40659997d59afbc6ed99~cs_noop.png"},{"title":"热舞风波后芬兰总理药检结果呈阴性","url":"https://www.toutiao.com/amos_land_page/?category_name=topic_innerflow&event_type=hot_board&log_pb=%7B%22category_name%22%3A%22topic_innerflow%22%2C%22cluster_type%22%3A%224%22%2C%22enter_from%22%3A%22click_category%22%2C%22entrance_hotspot%22%3A%22outside%22%2C%22event_type%22%3A%22hot_board%22%2C%22hot_board_cluster_id%22%3A%227134893237151465480%22%2C%22hot_board_impr_id%22%3A%2220220824054117010135119019165D8022%22%2C%22jump_page%22%3A%22hot_board_page%22%2C%22location%22%3A%22news_hot_card%22%2C%22page_location%22%3A%22hot_board_page%22%2C%22rank%22%3A%2246%22%2C%22source%22%3A%22trending_tab%22%2C%22style_id%22%3A%2240132%22%2C%22title%22%3A%22%E7%83%AD%E8%88%9E%E9%A3%8E%E6%B3%A2%E5%90%8E%E8%8A%AC%E5%85%B0%E6%80%BB%E7%90%86%E8%8D%AF%E6%A3%80%E7%BB%93%E6%9E%9C%E5%91%88%E9%98%B4%E6%80%A7%22%7D&rank=46&style_id=40132&topic_id=7134893237151465480","hot":"105454","icon":"","cover":"https://p3.toutiaoimg.com/img/tos-cn-i-qvj2lq49k0/4d66b0b47e224cd18b04bc264de05133~cs_noop.png"},{"title":"芬兰女总理被曝出新热舞视频","url":"https://www.toutiao.com/amos_land_page/?category_name=topic_innerflow&event_type=hot_board&log_pb=%7B%22category_name%22%3A%22topic_innerflow%22%2C%22cluster_type%22%3A%226%22%2C%22enter_from%22%3A%22click_category%22%2C%22entrance_hotspot%22%3A%22outside%22%2C%22event_type%22%3A%22hot_board%22%2C%22hot_board_cluster_id%22%3A%227135011144544026665%22%2C%22hot_board_impr_id%22%3A%2220220824054117010135119019165D8022%22%2C%22jump_page%22%3A%22hot_board_page%22%2C%22location%22%3A%22news_hot_card%22%2C%22page_location%22%3A%22hot_board_page%22%2C%22rank%22%3A%2247%22%2C%22source%22%3A%22trending_tab%22%2C%22style_id%22%3A%2240132%22%2C%22title%22%3A%22%E8%8A%AC%E5%85%B0%E5%A5%B3%E6%80%BB%E7%90%86%E8%A2%AB%E6%9B%9D%E5%87%BA%E6%96%B0%E7%83%AD%E8%88%9E%E8%A7%86%E9%A2%91%22%7D&rank=47&style_id=40132&topic_id=7135011144544026665","hot":"95418","icon":"","cover":"https://p9.toutiaoimg.com/img/tos-cn-i-qvj2lq49k0/885b76410eaa43168aa724986db5f30f~cs_noop.png"},{"title":"歌手席琳迪翁近况","url":"https://www.toutiao.com/amos_land_page/?category_name=topic_innerflow&event_type=hot_board&log_pb=%7B%22category_name%22%3A%22topic_innerflow%22%2C%22cluster_type%22%3A%221%22%2C%22enter_from%22%3A%22click_category%22%2C%22entrance_hotspot%22%3A%22outside%22%2C%22event_type%22%3A%22hot_board%22%2C%22hot_board_cluster_id%22%3A%227134999916723568651%22%2C%22hot_board_impr_id%22%3A%2220220824054117010135119019165D8022%22%2C%22jump_page%22%3A%22hot_board_page%22%2C%22location%22%3A%22news_hot_card%22%2C%22page_location%22%3A%22hot_board_page%22%2C%22rank%22%3A%2248%22%2C%22source%22%3A%22trending_tab%22%2C%22style_id%22%3A%2240132%22%2C%22title%22%3A%22%E6%AD%8C%E6%89%8B%E5%B8%AD%E7%90%B3%E8%BF%AA%E7%BF%81%E8%BF%91%E5%86%B5%22%7D&rank=48&style_id=40132&topic_id=7134999916723568651","hot":"86338","icon":"","cover":"https://p6.toutiaoimg.com/img/top-static-files-outer/breaknews/7ccbf376-b3db-4f7c-be6b-09ef3dd019f8~cs_noop.png"},{"title":"新疆一小区云雾缭绕：是雾森系统","url":"https://www.toutiao.com/amos_land_page/?category_name=topic_innerflow&event_type=hot_board&log_pb=%7B%22category_name%22%3A%22topic_innerflow%22%2C%22cluster_type%22%3A%222%22%2C%22enter_from%22%3A%22click_category%22%2C%22entrance_hotspot%22%3A%22outside%22%2C%22event_type%22%3A%22hot_board%22%2C%22hot_board_cluster_id%22%3A%227134900670099881999%22%2C%22hot_board_impr_id%22%3A%2220220824054117010135119019165D8022%22%2C%22jump_page%22%3A%22hot_board_page%22%2C%22location%22%3A%22news_hot_card%22%2C%22page_location%22%3A%22hot_board_page%22%2C%22rank%22%3A%2249%22%2C%22source%22%3A%22trending_tab%22%2C%22style_id%22%3A%2240132%22%2C%22title%22%3A%22%E6%96%B0%E7%96%86%E4%B8%80%E5%B0%8F%E5%8C%BA%E4%BA%91%E9%9B%BE%E7%BC%AD%E7%BB%95%EF%BC%9A%E6%98%AF%E9%9B%BE%E6%A3%AE%E7%B3%BB%E7%BB%9F%22%7D&rank=49&style_id=40132&topic_id=7134900670099881999","hot":"78122","icon":"","cover":"https://p26.toutiaoimg.com/img/top-static-files-outer/breaknews/4ef616e9-c1a4-43cd-8f81-a7ec3a46db84~cs_noop.png"},{"title":"中国气象局调增雨飞机驰援重庆抗旱","url":"https://www.toutiao.com/amos_land_page/?category_name=topic_innerflow&event_type=hot_board&log_pb=%7B%22category_name%22%3A%22topic_innerflow%22%2C%22cluster_type%22%3A%228%22%2C%22enter_from%22%3A%22click_category%22%2C%22entrance_hotspot%22%3A%22outside%22%2C%22event_type%22%3A%22hot_board%22%2C%22hot_board_cluster_id%22%3A%227134991562668572679%22%2C%22hot_board_impr_id%22%3A%2220220824054117010135119019165D8022%22%2C%22jump_page%22%3A%22hot_board_page%22%2C%22location%22%3A%22news_hot_card%22%2C%22page_location%22%3A%22hot_board_page%22%2C%22rank%22%3A%2250%22%2C%22source%22%3A%22trending_tab%22%2C%22style_id%22%3A%2240132%22%2C%22title%22%3A%22%E4%B8%AD%E5%9B%BD%E6%B0%94%E8%B1%A1%E5%B1%80%E8%B0%83%E5%A2%9E%E9%9B%A8%E9%A3%9E%E6%9C%BA%E9%A9%B0%E6%8F%B4%E9%87%8D%E5%BA%86%E6%8A%97%E6%97%B1%22%7D&rank=50&style_id=40132&topic_id=7134991562668572679","hot":"70688","icon":"","cover":"https://p9.toutiaoimg.com/img/tos-cn-i-qvj2lq49k0/514892da7c1843f3bbc1e4b725585eca~cs_noop.png"}]